[
  {
    "url_pagina": "https://www1.finanze.gov.it/finanze2/dipartimentopolitichefiscali/fiscalitalocale/nuova_imu/risultato.htm?lista=1&r=1&pagina=abruzzo.htm&cm=&pr=PE&anno=2025&cc=A008",
    "comune": "ABBATEGGIO",
    "codice_catastale": "A008",
    "provincia": "PE",
    "delibere": [
      {
        "anno_riferimento": 2025,
        "num_delibera": "10",
        "data_delibera": "27-02-2025",
        "data_pubblicazione": "12-03-2025",
        "codice_tributo": "IMU",
        "note": "",
        "nome_prospetto": "7464_DIMUNIC-01pe25a008d.pdf",
        "link_prospetto": "https://www1.finanze.gov.it/finanze2/dipartimentopolitichefiscali/fiscalitalocale/nuova_imu/download_lib.php?key=0900f230807a5fa9&nome=7464_DIMUNIC-01pe25a008d.pdf",
        "key_documentum": "0900f230807a5fa9"
      }
    ]
  },
  {
    "url_pagina": "https://www1.finanze.gov.it/finanze2/dipartimentopolitichefiscali/fiscalitalocale/nuova_imu/risultato.htm?lista=1&r=1&pagina=abruzzo.htm&cm=&pr=PE&anno=2025&cc=A120",
    "comune": "ALANNO",
    "codice_catastale": "A120",
    "provincia": "PE",
    "delibere": [
      {
        "anno_riferimento": 2025,
        "num_delibera": "79",
        "data_delibera": "23-12-2024",
        "data_pubblicazione": "03-02-2025",
        "codice_tributo": "IMU",
        "note": "",
        "nome_prospetto": "2447_DIMUNIC-01pe25a120d.pdf",
        "link_prospetto": "https://www1.finanze.gov.it/finanze2/dipartimentopolitichefiscali/fiscalitalocale/nuova_imu/download_lib.php?key=0900f23080761dd9&nome=2447_DIMUNIC-01pe25a120d.pdf",
        "key_documentum": "0900f23080761dd9"
      }
    ]
  },
  {
    "url_pagina": "https://www1.finanze.gov.it/finanze2/dipartimentopolitichefiscali/fiscalitalocale/nuova_imu/risultato.htm?lista=1&r=1&pagina=abruzzo.htm&cm=&pr=PE&anno=2025&cc=A945",
    "comune": "BOLOGNANO",
    "codice_catastale": "A945",
    "provincia": "PE",
    "delibere": [
      {
        "anno_riferimento": 2025,
        "num_delibera": "18",
        "data_delibera": "27-12-2024",
        "data_pubblicazione": "26-02-2025",
        "codice_tributo": "IMU",
        "note": "",
        "nome_prospetto": "6030_DIMUNIC-01pe25a945d.pdf",
        "link_prospetto": "https://www1.finanze.gov.it/finanze2/dipartimentopolitichefiscali/fiscalitalocale/nuova_imu/download_lib.php?key=0900f2308079440d&nome=6030_DIMUNIC-01pe25a945d.pdf",
        "key_documentum": "0900f2308079440d"
      }
    ]
  },
  {
    "url_pagina": "https://www1.finanze.gov.it/finanze2/dipartimentopolitichefiscali/fiscalitalocale/nuova_imu/risultato.htm?lista=1&r=1&pagina=abruzzo.htm&cm=&pr=PE&anno=2025&cc=B193",
    "comune": "BRITTOLI",
    "codice_catastale": "B193",
    "provincia": "PE",
    "delibere": [
      {
        "anno_riferimento": 2025,
        "num_delibera": "9",
        "data_delibera": "28-02-2025",
        "data_pubblicazione": "05-03-2025",
        "codice_tributo": "IMU",
        "note": "",
        "nome_prospetto": "8648_DIMUNIC-01pe25b193d.pdf",
        "link_prospetto": "https://www1.finanze.gov.it/finanze2/dipartimentopolitichefiscali/fiscalitalocale/nuova_imu/download_lib.php?key=0900f2308079d75b&nome=8648_DIMUNIC-01pe25b193d.pdf",
        "key_documentum": "0900f2308079d75b"
      }
    ]
  },
  {
    "url_pagina": "https://www1.finanze.gov.it/finanze2/dipartimentopolitichefiscali/fiscalitalocale/nuova_imu/risultato.htm?lista=1&r=1&pagina=abruzzo.htm&cm=&pr=PE&anno=2025&cc=B294",
    "comune": "BUSSI SUL TIRINO",
    "codice_catastale": "B294",
    "provincia": "PE",
    "delibere": [
      {
        "anno_riferimento": 2025,
        "num_delibera": "33",
        "data_delibera": "20-12-2024",
        "data_pubblicazione": "09-01-2025",
        "codice_tributo": "IMU",
        "note": "",
        "nome_prospetto": "2724_DIMUNIC-01pe25b294d.pdf",
        "link_prospetto": "https://www1.finanze.gov.it/finanze2/dipartimentopolitichefiscali/fiscalitalocale/nuova_imu/download_lib.php?key=0900f23080750eaf&nome=2724_DIMUNIC-01pe25b294d.pdf",
        "key_documentum": "0900f23080750eaf"
      }
    ]
  },
  {
    "url_pagina": "https://www1.finanze.gov.it/finanze2/dipartimentopolitichefiscali/fiscalitalocale/nuova_imu/risultato.htm?lista=1&r=1&pagina=abruzzo.htm&cm=&pr=PE&anno=2025&cc=B681",
    "comune": "CAPPELLE SUL TAVO",
    "codice_catastale": "B681",
    "provincia": "PE",
    "delibere": [
      {
        "anno_riferimento": 2025,
        "num_delibera": "26",
        "data_delibera": "18-12-2024",
        "data_pubblicazione": "13-02-2025",
        "codice_tributo": "IMU",
        "note": "",
        "nome_prospetto": "3282_DIMUNIC-01pe25b681d.pdf",
        "link_prospetto": "https://www1.finanze.gov.it/finanze2/dipartimentopolitichefiscali/fiscalitalocale/nuova_imu/download_lib.php?key=0900f2308078167b&nome=3282_DIMUNIC-01pe25b681d.pdf",
        "key_documentum": "0900f2308078167b"
      }
    ]
  },
  {
    "url_pagina": "https://www1.finanze.gov.it/finanze2/dipartimentopolitichefiscali/fiscalitalocale/nuova_imu/risultato.htm?lista=1&r=1&pagina=abruzzo.htm&cm=&pr=PE&anno=2025&cc=B722",
    "comune": "CARAMANICO TERME",
    "codice_catastale": "B722",
    "provincia": "PE",
    "delibere": [
      {
        "anno_riferimento": 2025,
        "num_delibera": "48",
        "data_delibera": "30-12-2024",
        "data_pubblicazione": "18-02-2025",
        "codice_tributo": "IMU",
        "note": "",
        "nome_prospetto": "8052_DIMUNIC-01pe25b722d.pdf",
        "link_prospetto": "https://www1.finanze.gov.it/finanze2/dipartimentopolitichefiscali/fiscalitalocale/nuova_imu/download_lib.php?key=0900f23080786d15&nome=8052_DIMUNIC-01pe25b722d.pdf",
        "key_documentum": "0900f23080786d15"
      }
    ]
  },
  {
    "url_pagina": "https://www1.finanze.gov.it/finanze2/dipartimentopolitichefiscali/fiscalitalocale/nuova_imu/risultato.htm?lista=1&r=1&pagina=abruzzo.htm&cm=&pr=PE&anno=2025&cc=B827",
    "comune": "CARPINETO DELLA NORA",
    "codice_catastale": "B827",
    "provincia": "PE",
    "delibere": [
      {
        "anno_riferimento": 2025,
        "num_delibera": "14",
        "data_delibera": "27-12-2024",
        "data_pubblicazione": "03-02-2025",
        "codice_tributo": "IMU",
        "note": "",
        "nome_prospetto": "3402_DIMUNIC-01pe25b827d.pdf",
        "link_prospetto": "https://www1.finanze.gov.it/finanze2/dipartimentopolitichefiscali/fiscalitalocale/nuova_imu/download_lib.php?key=0900f230807614b1&nome=3402_DIMUNIC-01pe25b827d.pdf",
        "key_documentum": "0900f230807614b1"
      }
    ]
  },
  {
    "url_pagina": "https://www1.finanze.gov.it/finanze2/dipartimentopolitichefiscali/fiscalitalocale/nuova_imu/risultato.htm?lista=1&r=1&pagina=abruzzo.htm&cm=&pr=PE&anno=2025&cc=C308",
    "comune": "CASTIGLIONE A CASAURIA",
    "codice_catastale": "C308",
    "provincia": "PE",
    "delibere": [
      {
        "anno_riferimento": 2025,
        "num_delibera": "46",
        "data_delibera": "30-12-2024",
        "data_pubblicazione": "21-02-2025",
        "codice_tributo": "IMU",
        "note": "",
        "nome_prospetto": "4433_DIMUNIC-01pe25c308d.pdf",
        "link_prospetto": "https://www1.finanze.gov.it/finanze2/dipartimentopolitichefiscali/fiscalitalocale/nuova_imu/download_lib.php?key=0900f2308078d697&nome=4433_DIMUNIC-01pe25c308d.pdf",
        "key_documentum": "0900f2308078d697"
      }
    ]
  },
  {
    "url_pagina": "https://www1.finanze.gov.it/finanze2/dipartimentopolitichefiscali/fiscalitalocale/nuova_imu/risultato.htm?lista=1&r=1&pagina=abruzzo.htm&cm=&pr=PE&anno=2025&cc=C354",
    "comune": "CATIGNANO",
    "codice_catastale": "C354",
    "provincia": "PE",
    "delibere": [
      {
        "anno_riferimento": 2025,
        "num_delibera": "1",
        "data_delibera": "21-02-2025",
        "data_pubblicazione": "25-02-2025",
        "codice_tributo": "IMU",
        "note": "",
        "nome_prospetto": "8071_DIMUNIC-01pe25c354d.pdf",
        "link_prospetto": "https://www1.finanze.gov.it/finanze2/dipartimentopolitichefiscali/fiscalitalocale/nuova_imu/download_lib.php?key=0900f2308078f7e4&nome=8071_DIMUNIC-01pe25c354d.pdf",
        "key_documentum": "0900f2308078f7e4"
      }
    ]
  },
  {
    "url_pagina": "https://www1.finanze.gov.it/finanze2/dipartimentopolitichefiscali/fiscalitalocale/nuova_imu/risultato.htm?lista=1&r=1&pagina=abruzzo.htm&cm=&pr=PE&anno=2025&cc=C474",
    "comune": "CEPAGATTI",
    "codice_catastale": "C474",
    "provincia": "PE",
    "delibere": [
      {
        "anno_riferimento": 2025,
        "num_delibera": "59",
        "data_delibera": "30-12-2024",
        "data_pubblicazione": "07-02-2025",
        "codice_tributo": "IMU",
        "note": "",
        "nome_prospetto": "760_DIMUNIC-01pe25c474d.pdf",
        "link_prospetto": "https://www1.finanze.gov.it/finanze2/dipartimentopolitichefiscali/fiscalitalocale/nuova_imu/download_lib.php?key=0900f23080761937&nome=760_DIMUNIC-01pe25c474d.pdf",
        "key_documentum": "0900f23080761937"
      }
    ]
  },
  {
    "url_pagina": "https://www1.finanze.gov.it/finanze2/dipartimentopolitichefiscali/fiscalitalocale/nuova_imu/risultato.htm?lista=1&r=1&pagina=abruzzo.htm&cm=&pr=PE&anno=2025&cc=C750",
    "comune": "CITTA' SANT'ANGELO",
    "codice_catastale": "C750",
    "provincia": "PE",
    "delibere": [
      {
        "anno_riferimento": 2025,
        "num_delibera": "63",
        "data_delibera": "27-11-2024",
        "data_pubblicazione": "19-12-2024",
        "codice_tributo": "IMU",
        "note": "",
        "nome_prospetto": "1238_DIMUNIC-01pe25c750d.pdf",
        "link_prospetto": "https://www1.finanze.gov.it/finanze2/dipartimentopolitichefiscali/fiscalitalocale/nuova_imu/download_lib.php?key=0900f23080741cf1&nome=1238_DIMUNIC-01pe25c750d.pdf",
        "key_documentum": "0900f23080741cf1"
      },
      {
        "anno_riferimento": 2025,
        "num_delibera": "63",
        "data_delibera": "27-11-2024",
        "data_pubblicazione": "26-02-2025",
        "codice_tributo": "IMU",
        "note": "ERRATA CORRIGE PER CORREZIONE DATI PROSPETTO",
        "nome_prospetto": "7917_DIMUNIC-01pe25c750d.pdf",
        "link_prospetto": "https://www1.finanze.gov.it/finanze2/dipartimentopolitichefiscali/fiscalitalocale/nuova_imu/download_lib.php?key=0900f23080782f30&nome=7917_DIMUNIC-01pe25c750d.pdf",
        "key_documentum": "0900f23080782f30"
      }
    ]
  },
  {
    "url_pagina": "https://www1.finanze.gov.it/finanze2/dipartimentopolitichefiscali/fiscalitalocale/nuova_imu/risultato.htm?lista=1&r=1&pagina=abruzzo.htm&cm=&pr=PE&anno=2025&cc=C771",
    "comune": "CIVITAQUANA",
    "codice_catastale": "C771",
    "provincia": "PE",
    "delibere": [
      {
        "anno_riferimento": 2025,
        "num_delibera": "23",
        "data_delibera": "20-12-2024",
        "data_pubblicazione": "10-02-2025",
        "codice_tributo": "IMU",
        "note": "",
        "nome_prospetto": "4887_DIMUNIC-01pe25c771d.pdf",
        "link_prospetto": "https://www1.finanze.gov.it/finanze2/dipartimentopolitichefiscali/fiscalitalocale/nuova_imu/download_lib.php?key=0900f23080774c64&nome=4887_DIMUNIC-01pe25c771d.pdf",
        "key_documentum": "0900f23080774c64"
      },
      {
        "anno_riferimento": 2025,
        "num_delibera": "23",
        "data_delibera": "20-12-2024",
        "data_pubblicazione": "25-02-2025",
        "codice_tributo": "IMU",
        "note": "ERRATA CORRIGE PER CORREZIONE DATI PROSPETTO",
        "nome_prospetto": "8456_DIMUNIC-01pe25c771d.pdf",
        "link_prospetto": "https://www1.finanze.gov.it/finanze2/dipartimentopolitichefiscali/fiscalitalocale/nuova_imu/download_lib.php?key=0900f23080791c30&nome=8456_DIMUNIC-01pe25c771d.pdf",
        "key_documentum": "0900f23080791c30"
      }
    ]
  },
  {
    "url_pagina": "https://www1.finanze.gov.it/finanze2/dipartimentopolitichefiscali/fiscalitalocale/nuova_imu/risultato.htm?lista=1&r=1&pagina=abruzzo.htm&cm=&pr=PE&anno=2025&cc=C779",
    "comune": "CIVITELLA CASANOVA",
    "codice_catastale": "C779",
    "provincia": "PE",
    "delibere": [
      {
        "anno_riferimento": 2025,
        "num_delibera": "21",
        "data_delibera": "10-12-2024",
        "data_pubblicazione": "28-02-2025",
        "codice_tributo": "IMU",
        "note": "",
        "nome_prospetto": "4812_DIMUNIC-01pe25c779d.pdf",
        "link_prospetto": "https://www1.finanze.gov.it/finanze2/dipartimentopolitichefiscali/fiscalitalocale/nuova_imu/download_lib.php?key=0900f23080797d1e&nome=4812_DIMUNIC-01pe25c779d.pdf",
        "key_documentum": "0900f23080797d1e"
      }
    ]
  },
  {
    "url_pagina": "https://www1.finanze.gov.it/finanze2/dipartimentopolitichefiscali/fiscalitalocale/nuova_imu/risultato.htm?lista=1&r=1&pagina=abruzzo.htm&cm=&pr=PE&anno=2025&cc=C853",
    "comune": "COLLECORVINO",
    "codice_catastale": "C853",
    "provincia": "PE",
    "delibere": [
      {
        "anno_riferimento": 2025,
        "num_delibera": "7",
        "data_delibera": "27-02-2025",
        "data_pubblicazione": "28-02-2025",
        "codice_tributo": "IMU",
        "note": "",
        "nome_prospetto": "8088_DIMUNIC-01pe25c853d.pdf",
        "link_prospetto": "https://www1.finanze.gov.it/finanze2/dipartimentopolitichefiscali/fiscalitalocale/nuova_imu/download_lib.php?key=0900f23080796e2f&nome=8088_DIMUNIC-01pe25c853d.pdf",
        "key_documentum": "0900f23080796e2f"
      }
    ]
  },
  {
    "url_pagina": "https://www1.finanze.gov.it/finanze2/dipartimentopolitichefiscali/fiscalitalocale/nuova_imu/risultato.htm?lista=1&r=1&pagina=abruzzo.htm&cm=&pr=PE&anno=2025&cc=D078",
    "comune": "CORVARA",
    "codice_catastale": "D078",
    "provincia": "PE",
    "delibere": [
      {
        "anno_riferimento": 2025,
        "num_delibera": "19",
        "data_delibera": "30-12-2024",
        "data_pubblicazione": "10-02-2025",
        "codice_tributo": "IMU",
        "note": "",
        "nome_prospetto": "6606_DIMUNIC-01pe25d078d.pdf",
        "link_prospetto": "https://www1.finanze.gov.it/finanze2/dipartimentopolitichefiscali/fiscalitalocale/nuova_imu/download_lib.php?key=0900f2308077a24e&nome=6606_DIMUNIC-01pe25d078d.pdf",
        "key_documentum": "0900f2308077a24e"
      }
    ]
  },
  {
    "url_pagina": "https://www1.finanze.gov.it/finanze2/dipartimentopolitichefiscali/fiscalitalocale/nuova_imu/risultato.htm?lista=1&r=1&pagina=abruzzo.htm&cm=&pr=PE&anno=2025&cc=D201",
    "comune": "CUGNOLI",
    "codice_catastale": "D201",
    "provincia": "PE",
    "delibere": [
      {
        "anno_riferimento": 2025,
        "num_delibera": "19",
        "data_delibera": "28-12-2024",
        "data_pubblicazione": "25-02-2025",
        "codice_tributo": "IMU",
        "note": "",
        "nome_prospetto": "910_DIMUNIC-01pe25d201d.pdf",
        "link_prospetto": "https://www1.finanze.gov.it/finanze2/dipartimentopolitichefiscali/fiscalitalocale/nuova_imu/download_lib.php?key=0900f230807919e4&nome=910_DIMUNIC-01pe25d201d.pdf",
        "key_documentum": "0900f230807919e4"
      }
    ]
  },
  {
    "url_pagina": "https://www1.finanze.gov.it/finanze2/dipartimentopolitichefiscali/fiscalitalocale/nuova_imu/risultato.htm?lista=1&r=1&pagina=abruzzo.htm&cm=&pr=PE&anno=2025&cc=D394",
    "comune": "ELICE",
    "codice_catastale": "D394",
    "provincia": "PE",
    "delibere": [
      {
        "anno_riferimento": 2025,
        "num_delibera": "28",
        "data_delibera": "30-12-2024",
        "data_pubblicazione": "27-02-2025",
        "codice_tributo": "IMU",
        "note": "",
        "nome_prospetto": "5142_DIMUNIC-01pe25d394d.pdf",
        "link_prospetto": "https://www1.finanze.gov.it/finanze2/dipartimentopolitichefiscali/fiscalitalocale/nuova_imu/download_lib.php?key=0900f23080795fa6&nome=5142_DIMUNIC-01pe25d394d.pdf",
        "key_documentum": "0900f23080795fa6"
      }
    ]
  },
  {
    "url_pagina": "https://www1.finanze.gov.it/finanze2/dipartimentopolitichefiscali/fiscalitalocale/nuova_imu/risultato.htm?lista=1&r=1&pagina=abruzzo.htm&cm=&pr=PE&anno=2025&cc=D501",
    "comune": "FARINDOLA",
    "codice_catastale": "D501",
    "provincia": "PE",
    "delibere": [
      {
        "anno_riferimento": 2025,
        "num_delibera": "2",
        "data_delibera": "21-02-2025",
        "data_pubblicazione": "20-03-2025",
        "codice_tributo": "IMU",
        "note": "",
        "nome_prospetto": "7526_DIMUNIC-01pe25d501d.pdf",
        "link_prospetto": "https://www1.finanze.gov.it/finanze2/dipartimentopolitichefiscali/fiscalitalocale/nuova_imu/download_lib.php?key=0900f230807b28f3&nome=7526_DIMUNIC-01pe25d501d.pdf",
        "key_documentum": "0900f230807b28f3"
      }
    ]
  },
  {
    "url_pagina": "https://www1.finanze.gov.it/finanze2/dipartimentopolitichefiscali/fiscalitalocale/nuova_imu/risultato.htm?lista=1&r=1&pagina=abruzzo.htm&cm=&pr=PE&anno=2025&cc=E558",
    "comune": "LETTOMANOPPELLO",
    "codice_catastale": "E558",
    "provincia": "PE",
    "delibere": [
      {
        "anno_riferimento": 2025,
        "num_delibera": "49",
        "data_delibera": "23-12-2024",
        "data_pubblicazione": "06-02-2025",
        "codice_tributo": "IMU",
        "note": "",
        "nome_prospetto": "5205_DIMUNIC-01pe25e558d.pdf",
        "link_prospetto": "https://www1.finanze.gov.it/finanze2/dipartimentopolitichefiscali/fiscalitalocale/nuova_imu/download_lib.php?key=0900f23080775834&nome=5205_DIMUNIC-01pe25e558d.pdf",
        "key_documentum": "0900f23080775834"
      }
    ]
  },
  {
    "url_pagina": "https://www1.finanze.gov.it/finanze2/dipartimentopolitichefiscali/fiscalitalocale/nuova_imu/risultato.htm?lista=1&r=1&pagina=abruzzo.htm&cm=&pr=PE&anno=2025&cc=E691",
    "comune": "LORETO APRUTINO",
    "codice_catastale": "E691",
    "provincia": "PE",
    "delibere": [
      {
        "anno_riferimento": 2025,
        "num_delibera": "55",
        "data_delibera": "02-12-2024",
        "data_pubblicazione": "03-01-2025",
        "codice_tributo": "IMU",
        "note": "",
        "nome_prospetto": "649_DIMUNIC-01pe25e691d.pdf",
        "link_prospetto": "https://www1.finanze.gov.it/finanze2/dipartimentopolitichefiscali/fiscalitalocale/nuova_imu/download_lib.php?key=0900f2308074cf9a&nome=649_DIMUNIC-01pe25e691d.pdf",
        "key_documentum": "0900f2308074cf9a"
      }
    ]
  },
  {
    "url_pagina": "https://www1.finanze.gov.it/finanze2/dipartimentopolitichefiscali/fiscalitalocale/nuova_imu/risultato.htm?lista=1&r=1&pagina=abruzzo.htm&cm=&pr=PE&anno=2025&cc=E892",
    "comune": "MANOPPELLO",
    "codice_catastale": "E892",
    "provincia": "PE",
    "delibere": [
      {
        "anno_riferimento": 2025,
        "num_delibera": "67",
        "data_delibera": "18-12-2024",
        "data_pubblicazione": "07-02-2025",
        "codice_tributo": "IMU",
        "note": "",
        "nome_prospetto": "1677_DIMUNIC-01pe25e892d.pdf",
        "link_prospetto": "https://www1.finanze.gov.it/finanze2/dipartimentopolitichefiscali/fiscalitalocale/nuova_imu/download_lib.php?key=0900f23080776732&nome=1677_DIMUNIC-01pe25e892d.pdf",
        "key_documentum": "0900f23080776732"
      }
    ]
  },
  {
    "url_pagina": "https://www1.finanze.gov.it/finanze2/dipartimentopolitichefiscali/fiscalitalocale/nuova_imu/risultato.htm?lista=1&r=1&pagina=abruzzo.htm&cm=&pr=PE&anno=2025&cc=F441",
    "comune": "MONTEBELLO DI BERTONA",
    "codice_catastale": "F441",
    "provincia": "PE",
    "delibere": [
      {
        "anno_riferimento": 2025,
        "num_delibera": "41",
        "data_delibera": "18-12-2024",
        "data_pubblicazione": "13-02-2025",
        "codice_tributo": "IMU",
        "note": "",
        "nome_prospetto": "7842_DIMUNIC-01pe25f441d.pdf",
        "link_prospetto": "https://www1.finanze.gov.it/finanze2/dipartimentopolitichefiscali/fiscalitalocale/nuova_imu/download_lib.php?key=0900f23080781ece&nome=7842_DIMUNIC-01pe25f441d.pdf",
        "key_documentum": "0900f23080781ece"
      }
    ]
  },
  {
    "url_pagina": "https://www1.finanze.gov.it/finanze2/dipartimentopolitichefiscali/fiscalitalocale/nuova_imu/risultato.htm?lista=1&r=1&pagina=abruzzo.htm&cm=&pr=PE&anno=2025&cc=F646",
    "comune": "MONTESILVANO",
    "codice_catastale": "F646",
    "provincia": "PE",
    "delibere": [
      {
        "anno_riferimento": 2025,
        "num_delibera": "101",
        "data_delibera": "20-12-2024",
        "data_pubblicazione": "16-01-2025",
        "codice_tributo": "IMU",
        "note": "",
        "nome_prospetto": "1851_DIMUNIC-01pe25f646d.pdf",
        "link_prospetto": "https://www1.finanze.gov.it/finanze2/dipartimentopolitichefiscali/fiscalitalocale/nuova_imu/download_lib.php?key=0900f23080758bdc&nome=1851_DIMUNIC-01pe25f646d.pdf",
        "key_documentum": "0900f23080758bdc"
      }
    ]
  },
  {
    "url_pagina": "https://www1.finanze.gov.it/finanze2/dipartimentopolitichefiscali/fiscalitalocale/nuova_imu/risultato.htm?lista=1&r=1&pagina=abruzzo.htm&cm=&pr=PE&anno=2025&cc=F765",
    "comune": "MOSCUFO",
    "codice_catastale": "F765",
    "provincia": "PE",
    "delibere": [
      {
        "anno_riferimento": 2025,
        "num_delibera": "24",
        "data_delibera": "30-11-2024",
        "data_pubblicazione": "10-02-2025",
        "codice_tributo": "IMU",
        "note": "",
        "nome_prospetto": "2620_DIMUNIC-01pe25f765d.pdf",
        "link_prospetto": "https://www1.finanze.gov.it/finanze2/dipartimentopolitichefiscali/fiscalitalocale/nuova_imu/download_lib.php?key=0900f2308077973c&nome=2620_DIMUNIC-01pe25f765d.pdf",
        "key_documentum": "0900f2308077973c"
      }
    ]
  },
  {
    "url_pagina": "https://www1.finanze.gov.it/finanze2/dipartimentopolitichefiscali/fiscalitalocale/nuova_imu/risultato.htm?lista=1&r=1&pagina=abruzzo.htm&cm=&pr=PE&anno=2025&cc=F908",
    "comune": "NOCCIANO",
    "codice_catastale": "F908",
    "provincia": "PE",
    "delibere": [
      {
        "anno_riferimento": 2025,
        "num_delibera": "35",
        "data_delibera": "27-12-2024",
        "data_pubblicazione": "13-02-2025",
        "codice_tributo": "IMU",
        "note": "",
        "nome_prospetto": "7810_DIMUNIC-01pe25f908d.pdf",
        "link_prospetto": "https://www1.finanze.gov.it/finanze2/dipartimentopolitichefiscali/fiscalitalocale/nuova_imu/download_lib.php?key=0900f23080781393&nome=7810_DIMUNIC-01pe25f908d.pdf",
        "key_documentum": "0900f23080781393"
      }
    ]
  },
  {
    "url_pagina": "https://www1.finanze.gov.it/finanze2/dipartimentopolitichefiscali/fiscalitalocale/nuova_imu/risultato.htm?lista=1&r=1&pagina=abruzzo.htm&cm=&pr=PE&anno=2025&cc=G438",
    "comune": "PENNE",
    "codice_catastale": "G438",
    "provincia": "PE",
    "delibere": [
      {
        "anno_riferimento": 2025,
        "num_delibera": "56",
        "data_delibera": "23-12-2024",
        "data_pubblicazione": "03-02-2025",
        "codice_tributo": "IMU",
        "note": "",
        "nome_prospetto": "2872_DIMUNIC-01pe25g438d.pdf",
        "link_prospetto": "https://www1.finanze.gov.it/finanze2/dipartimentopolitichefiscali/fiscalitalocale/nuova_imu/download_lib.php?key=0900f2308075ecfa&nome=2872_DIMUNIC-01pe25g438d.pdf",
        "key_documentum": "0900f2308075ecfa"
      }
    ]
  },
  {
    "url_pagina": "https://www1.finanze.gov.it/finanze2/dipartimentopolitichefiscali/fiscalitalocale/nuova_imu/risultato.htm?lista=1&r=1&pagina=abruzzo.htm&cm=&pr=PE&anno=2025&cc=G482",
    "comune": "PESCARA",
    "codice_catastale": "G482",
    "provincia": "PE",
    "delibere": [
      {
        "anno_riferimento": 2025,
        "num_delibera": "25",
        "data_delibera": "27-02-2025",
        "data_pubblicazione": "13-03-2025",
        "codice_tributo": "IMU",
        "note": "",
        "nome_prospetto": "7121_DIMUNIC-01pe25g482d.pdf",
        "link_prospetto": "https://www1.finanze.gov.it/finanze2/dipartimentopolitichefiscali/fiscalitalocale/nuova_imu/download_lib.php?key=0900f230807a7994&nome=7121_DIMUNIC-01pe25g482d.pdf",
        "key_documentum": "0900f230807a7994"
      }
    ]
  },
  {
    "url_pagina": "https://www1.finanze.gov.it/finanze2/dipartimentopolitichefiscali/fiscalitalocale/nuova_imu/risultato.htm?lista=1&r=1&pagina=abruzzo.htm&cm=&pr=PE&anno=2025&cc=G499",
    "comune": "PESCOSANSONESCO",
    "codice_catastale": "G499",
    "provincia": "PE",
    "delibere": [
      {
        "anno_riferimento": 2025,
        "num_delibera": "21",
        "data_delibera": "27-12-2024",
        "data_pubblicazione": "27-02-2025",
        "codice_tributo": "IMU",
        "note": "",
        "nome_prospetto": "8606_DIMUNIC-01pe25g499d.pdf",
        "link_prospetto": "https://www1.finanze.gov.it/finanze2/dipartimentopolitichefiscali/fiscalitalocale/nuova_imu/download_lib.php?key=0900f2308079614f&nome=8606_DIMUNIC-01pe25g499d.pdf",
        "key_documentum": "0900f2308079614f"
      }
    ]
  },
  {
    "url_pagina": "https://www1.finanze.gov.it/finanze2/dipartimentopolitichefiscali/fiscalitalocale/nuova_imu/risultato.htm?lista=1&r=1&pagina=abruzzo.htm&cm=&pr=PE&anno=2025&cc=G555",
    "comune": "PIANELLA",
    "codice_catastale": "G555",
    "provincia": "PE",
    "delibere": [
      {
        "anno_riferimento": 2025,
        "num_delibera": "34",
        "data_delibera": "23-12-2024",
        "data_pubblicazione": "30-12-2024",
        "codice_tributo": "IMU",
        "note": "",
        "nome_prospetto": "1163_DIMUNIC-01pe25g555d.pdf",
        "link_prospetto": "https://www1.finanze.gov.it/finanze2/dipartimentopolitichefiscali/fiscalitalocale/nuova_imu/download_lib.php?key=0900f23080748eac&nome=1163_DIMUNIC-01pe25g555d.pdf",
        "key_documentum": "0900f23080748eac"
      }
    ]
  },
  {
    "url_pagina": "https://www1.finanze.gov.it/finanze2/dipartimentopolitichefiscali/fiscalitalocale/nuova_imu/risultato.htm?lista=1&r=1&pagina=abruzzo.htm&cm=&pr=PE&anno=2025&cc=G589",
    "comune": "PICCIANO",
    "codice_catastale": "G589",
    "provincia": "PE",
    "delibere": [
      {
        "anno_riferimento": 2025,
        "num_delibera": "3",
        "data_delibera": "24-01-2025",
        "data_pubblicazione": "13-02-2025",
        "codice_tributo": "IMU",
        "note": "",
        "nome_prospetto": "6812_DIMUNIC-01pe25g589d.pdf",
        "link_prospetto": "https://www1.finanze.gov.it/finanze2/dipartimentopolitichefiscali/fiscalitalocale/nuova_imu/download_lib.php?key=0900f23080781667&nome=6812_DIMUNIC-01pe25g589d.pdf",
        "key_documentum": "0900f23080781667"
      }
    ]
  },
  {
    "url_pagina": "https://www1.finanze.gov.it/finanze2/dipartimentopolitichefiscali/fiscalitalocale/nuova_imu/risultato.htm?lista=1&r=1&pagina=abruzzo.htm&cm=&pr=PE&anno=2025&cc=G621",
    "comune": "PIETRANICO",
    "codice_catastale": "G621",
    "provincia": "PE",
    "delibere": [
      {
        "anno_riferimento": 2025,
        "num_delibera": "7",
        "data_delibera": "28-02-2025",
        "data_pubblicazione": "03-03-2025",
        "codice_tributo": "IMU",
        "note": "",
        "nome_prospetto": "8747_DIMUNIC-01pe25g621d.pdf",
        "link_prospetto": "https://www1.finanze.gov.it/finanze2/dipartimentopolitichefiscali/fiscalitalocale/nuova_imu/download_lib.php?key=0900f23080799c98&nome=8747_DIMUNIC-01pe25g621d.pdf",
        "key_documentum": "0900f23080799c98"
      }
    ]
  },
  {
    "url_pagina": "https://www1.finanze.gov.it/finanze2/dipartimentopolitichefiscali/fiscalitalocale/nuova_imu/risultato.htm?lista=1&r=1&pagina=abruzzo.htm&cm=&pr=PE&anno=2025&cc=G878",
    "comune": "POPOLI TERME",
    "codice_catastale": "G878",
    "provincia": "PE",
    "delibere": [
      {
        "anno_riferimento": 2025,
        "num_delibera": "4",
        "data_delibera": "23-01-2025",
        "data_pubblicazione": "13-02-2025",
        "codice_tributo": "IMU",
        "note": "",
        "nome_prospetto": "7052_DIMUNIC-01pe25g878d.pdf",
        "link_prospetto": "https://www1.finanze.gov.it/finanze2/dipartimentopolitichefiscali/fiscalitalocale/nuova_imu/download_lib.php?key=0900f23080769b3c&nome=7052_DIMUNIC-01pe25g878d.pdf",
        "key_documentum": "0900f23080769b3c"
      },
      {
        "anno_riferimento": 2025,
        "num_delibera": "4",
        "data_delibera": "23-01-2025",
        "data_pubblicazione": "26-02-2025",
        "codice_tributo": "IMU",
        "note": "ERRATA CORRIGE PER CORREZIONE DATI PROSPETTO",
        "nome_prospetto": "7813_DIMUNIC-01pe25g878d.pdf",
        "link_prospetto": "https://www1.finanze.gov.it/finanze2/dipartimentopolitichefiscali/fiscalitalocale/nuova_imu/download_lib.php?key=0900f230807816d8&nome=7813_DIMUNIC-01pe25g878d.pdf",
        "key_documentum": "0900f230807816d8"
      }
    ]
  },
  {
    "url_pagina": "https://www1.finanze.gov.it/finanze2/dipartimentopolitichefiscali/fiscalitalocale/nuova_imu/risultato.htm?lista=1&r=1&pagina=abruzzo.htm&cm=&pr=PE&anno=2025&cc=H425",
    "comune": "ROCCAMORICE",
    "codice_catastale": "H425",
    "provincia": "PE",
    "delibere": [
      {
        "anno_riferimento": 2025,
        "num_delibera": "3",
        "data_delibera": "27-01-2025",
        "data_pubblicazione": "26-02-2025",
        "codice_tributo": "IMU",
        "note": "",
        "nome_prospetto": "7198_DIMUNIC-01pe25h425d.pdf",
        "link_prospetto": "https://www1.finanze.gov.it/finanze2/dipartimentopolitichefiscali/fiscalitalocale/nuova_imu/download_lib.php?key=0900f230807940bd&nome=7198_DIMUNIC-01pe25h425d.pdf",
        "key_documentum": "0900f230807940bd"
      }
    ]
  },
  {
    "url_pagina": "https://www1.finanze.gov.it/finanze2/dipartimentopolitichefiscali/fiscalitalocale/nuova_imu/risultato.htm?lista=1&r=1&pagina=abruzzo.htm&cm=&pr=PE&anno=2025&cc=H562",
    "comune": "ROSCIANO",
    "codice_catastale": "H562",
    "provincia": "PE",
    "delibere": [
      {
        "anno_riferimento": 2025,
        "num_delibera": "54",
        "data_delibera": "23-12-2024",
        "data_pubblicazione": "04-02-2025",
        "codice_tributo": "IMU",
        "note": "",
        "nome_prospetto": "4080_DIMUNIC-01pe25h562d.pdf",
        "link_prospetto": "https://www1.finanze.gov.it/finanze2/dipartimentopolitichefiscali/fiscalitalocale/nuova_imu/download_lib.php?key=0900f2308075e3f3&nome=4080_DIMUNIC-01pe25h562d.pdf",
        "key_documentum": "0900f2308075e3f3"
      }
    ]
  },
  {
    "url_pagina": "https://www1.finanze.gov.it/finanze2/dipartimentopolitichefiscali/fiscalitalocale/nuova_imu/risultato.htm?lista=1&r=1&pagina=abruzzo.htm&cm=&pr=PE&anno=2025&cc=H715",
    "comune": "SALLE",
    "codice_catastale": "H715",
    "provincia": "PE",
    "delibere": [
      {
        "anno_riferimento": 2025,
        "num_delibera": "32",
        "data_delibera": "20-12-2024",
        "data_pubblicazione": "14-02-2025",
        "codice_tributo": "IMU",
        "note": "",
        "nome_prospetto": "4468_DIMUNIC-01pe25h715d.pdf",
        "link_prospetto": "https://www1.finanze.gov.it/finanze2/dipartimentopolitichefiscali/fiscalitalocale/nuova_imu/download_lib.php?key=0900f230807839c2&nome=4468_DIMUNIC-01pe25h715d.pdf",
        "key_documentum": "0900f230807839c2"
      }
    ]
  },
  {
    "url_pagina": "https://www1.finanze.gov.it/finanze2/dipartimentopolitichefiscali/fiscalitalocale/nuova_imu/risultato.htm?lista=1&r=1&pagina=abruzzo.htm&cm=&pr=PE&anno=2025&cc=I376",
    "comune": "SAN VALENTINO IN ABRUZZO CITERIORE",
    "codice_catastale": "I376",
    "provincia": "PE",
    "delibere": [
      {
        "anno_riferimento": 2025,
        "num_delibera": "24",
        "data_delibera": "31-12-2024",
        "data_pubblicazione": "13-02-2025",
        "codice_tributo": "IMU",
        "note": "",
        "nome_prospetto": "6529_DIMUNIC-01pe25i376d.pdf",
        "link_prospetto": "https://www1.finanze.gov.it/finanze2/dipartimentopolitichefiscali/fiscalitalocale/nuova_imu/download_lib.php?key=0900f230807801d1&nome=6529_DIMUNIC-01pe25i376d.pdf",
        "key_documentum": "0900f230807801d1"
      }
    ]
  },
  {
    "url_pagina": "https://www1.finanze.gov.it/finanze2/dipartimentopolitichefiscali/fiscalitalocale/nuova_imu/risultato.htm?lista=1&r=1&pagina=abruzzo.htm&cm=&pr=PE&anno=2025&cc=I332",
    "comune": "SANT'EUFEMIA A MAIELLA",
    "codice_catastale": "I332",
    "provincia": "PE",
    "delibere": [
      {
        "anno_riferimento": 2025,
        "num_delibera": "41",
        "data_delibera": "18-12-2024",
        "data_pubblicazione": "21-02-2025",
        "codice_tributo": "IMU",
        "note": "",
        "nome_prospetto": "5372_DIMUNIC-01pe25i332d.pdf",
        "link_prospetto": "https://www1.finanze.gov.it/finanze2/dipartimentopolitichefiscali/fiscalitalocale/nuova_imu/download_lib.php?key=0900f2308078aeda&nome=5372_DIMUNIC-01pe25i332d.pdf",
        "key_documentum": "0900f2308078aeda"
      }
    ]
  },
  {
    "url_pagina": "https://www1.finanze.gov.it/finanze2/dipartimentopolitichefiscali/fiscalitalocale/nuova_imu/risultato.htm?lista=1&r=1&pagina=abruzzo.htm&cm=&pr=PE&anno=2025&cc=I482",
    "comune": "SCAFA",
    "codice_catastale": "I482",
    "provincia": "PE",
    "delibere": [
      {
        "anno_riferimento": 2025,
        "num_delibera": "30",
        "data_delibera": "19-12-2024",
        "data_pubblicazione": "07-02-2025",
        "codice_tributo": "IMU",
        "note": "",
        "nome_prospetto": "4199_DIMUNIC-01pe25i482d.pdf",
        "link_prospetto": "https://www1.finanze.gov.it/finanze2/dipartimentopolitichefiscali/fiscalitalocale/nuova_imu/download_lib.php?key=0900f23080777959&nome=4199_DIMUNIC-01pe25i482d.pdf",
        "key_documentum": "0900f23080777959"
      }
    ]
  },
  {
    "url_pagina": "https://www1.finanze.gov.it/finanze2/dipartimentopolitichefiscali/fiscalitalocale/nuova_imu/risultato.htm?lista=1&r=1&pagina=abruzzo.htm&cm=&pr=PE&anno=2025&cc=I649",
    "comune": "SERRAMONACESCA",
    "codice_catastale": "I649",
    "provincia": "PE",
    "delibere": [
      {
        "anno_riferimento": 2025,
        "num_delibera": "29",
        "data_delibera": "23-12-2024",
        "data_pubblicazione": "14-02-2025",
        "codice_tributo": "IMU",
        "note": "",
        "nome_prospetto": "7923_DIMUNIC-01pe25i649d.pdf",
        "link_prospetto": "https://www1.finanze.gov.it/finanze2/dipartimentopolitichefiscali/fiscalitalocale/nuova_imu/download_lib.php?key=0900f23080782fd3&nome=7923_DIMUNIC-01pe25i649d.pdf",
        "key_documentum": "0900f23080782fd3"
      },
      {
        "anno_riferimento": 2025,
        "num_delibera": "29",
        "data_delibera": "23-12-2024",
        "data_pubblicazione": "10-06-2025",
        "codice_tributo": "IMU",
        "note": "ERRATA CORRIGE PER CORREZIONE DATI PROSPETTO",
        "nome_prospetto": "10006_DIMUNIC-01pe25i649d.pdf",
        "link_prospetto": "https://www1.finanze.gov.it/finanze2/dipartimentopolitichefiscali/fiscalitalocale/nuova_imu/download_lib.php?key=0900f230808252d5&nome=10006_DIMUNIC-01pe25i649d.pdf",
        "key_documentum": "0900f230808252d5"
      }
    ]
  },
  {
    "url_pagina": "https://www1.finanze.gov.it/finanze2/dipartimentopolitichefiscali/fiscalitalocale/nuova_imu/risultato.htm?lista=1&r=1&pagina=abruzzo.htm&cm=&pr=PE&anno=2025&cc=I922",
    "comune": "SPOLTORE",
    "codice_catastale": "I922",
    "provincia": "PE",
    "delibere": [
      {
        "anno_riferimento": 2025,
        "num_delibera": "48",
        "data_delibera": "17-12-2024",
        "data_pubblicazione": "09-01-2025",
        "codice_tributo": "IMU",
        "note": "",
        "nome_prospetto": "2660_DIMUNIC-01pe25i922d.pdf",
        "link_prospetto": "https://www1.finanze.gov.it/finanze2/dipartimentopolitichefiscali/fiscalitalocale/nuova_imu/download_lib.php?key=0900f23080751143&nome=2660_DIMUNIC-01pe25i922d.pdf",
        "key_documentum": "0900f23080751143"
      }
    ]
  },
  {
    "url_pagina": "https://www1.finanze.gov.it/finanze2/dipartimentopolitichefiscali/fiscalitalocale/nuova_imu/risultato.htm?lista=1&r=1&pagina=abruzzo.htm&cm=&pr=PE&anno=2025&cc=L186",
    "comune": "TOCCO DA CASAURIA",
    "codice_catastale": "L186",
    "provincia": "PE",
    "delibere": [
      {
        "anno_riferimento": 2025,
        "num_delibera": "07",
        "data_delibera": "30-01-2025",
        "data_pubblicazione": "13-02-2025",
        "codice_tributo": "IMU",
        "note": "",
        "nome_prospetto": "2586_DIMUNIC-01pe25l186d.pdf",
        "link_prospetto": "https://www1.finanze.gov.it/finanze2/dipartimentopolitichefiscali/fiscalitalocale/nuova_imu/download_lib.php?key=0900f2308077f940&nome=2586_DIMUNIC-01pe25l186d.pdf",
        "key_documentum": "0900f2308077f940"
      }
    ]
  },
  {
    "url_pagina": "https://www1.finanze.gov.it/finanze2/dipartimentopolitichefiscali/fiscalitalocale/nuova_imu/risultato.htm?lista=1&r=1&pagina=abruzzo.htm&cm=&pr=PE&anno=2025&cc=L263",
    "comune": "TORRE DE' PASSERI",
    "codice_catastale": "L263",
    "provincia": "PE",
    "delibere": [
      {
        "anno_riferimento": 2025,
        "num_delibera": "38",
        "data_delibera": "28-12-2024",
        "data_pubblicazione": "13-02-2025",
        "codice_tributo": "IMU",
        "note": "",
        "nome_prospetto": "2641_DIMUNIC-01pe25l263d.pdf",
        "link_prospetto": "https://www1.finanze.gov.it/finanze2/dipartimentopolitichefiscali/fiscalitalocale/nuova_imu/download_lib.php?key=0900f2308077d506&nome=2641_DIMUNIC-01pe25l263d.pdf",
        "key_documentum": "0900f2308077d506"
      }
    ]
  },
  {
    "url_pagina": "https://www1.finanze.gov.it/finanze2/dipartimentopolitichefiscali/fiscalitalocale/nuova_imu/risultato.htm?lista=1&r=1&pagina=abruzzo.htm&cm=&pr=PE&anno=2025&cc=L475",
    "comune": "TURRIVALIGNANI",
    "codice_catastale": "L475",
    "provincia": "PE",
    "delibere": [
      {
        "anno_riferimento": 2025,
        "num_delibera": "28",
        "data_delibera": "19-12-2024",
        "data_pubblicazione": "04-02-2025",
        "codice_tributo": "IMU",
        "note": "",
        "nome_prospetto": "4666_DIMUNIC-01pe25l475d.pdf",
        "link_prospetto": "https://www1.finanze.gov.it/finanze2/dipartimentopolitichefiscali/fiscalitalocale/nuova_imu/download_lib.php?key=0900f2308075e410&nome=4666_DIMUNIC-01pe25l475d.pdf",
        "key_documentum": "0900f2308075e410"
      }
    ]
  },
  {
    "url_pagina": "https://www1.finanze.gov.it/finanze2/dipartimentopolitichefiscali/fiscalitalocale/nuova_imu/risultato.htm?lista=1&r=1&pagina=abruzzo.htm&cm=&pr=PE&anno=2025&cc=L846",
    "comune": "VICOLI",
    "codice_catastale": "L846",
    "provincia": "PE",
    "delibere": [
      {
        "anno_riferimento": 2025,
        "num_delibera": "31",
        "data_delibera": "20-12-2024",
        "data_pubblicazione": "26-02-2025",
        "codice_tributo": "IMU",
        "note": "",
        "nome_prospetto": "5543_DIMUNIC-01pe25l846d.pdf",
        "link_prospetto": "https://www1.finanze.gov.it/finanze2/dipartimentopolitichefiscali/fiscalitalocale/nuova_imu/download_lib.php?key=0900f23080781209&nome=5543_DIMUNIC-01pe25l846d.pdf",
        "key_documentum": "0900f23080781209"
      },
      {
        "anno_riferimento": 2025,
        "num_delibera": "31",
        "data_delibera": "20-12-2024",
        "data_pubblicazione": "27-02-2025",
        "codice_tributo": "IMU",
        "note": "ERRATA CORRIGE PER CORREZIONE DATI PROSPETTO",
        "nome_prospetto": "8625_DIMUNIC-01pe25l846d.pdf",
        "link_prospetto": "https://www1.finanze.gov.it/finanze2/dipartimentopolitichefiscali/fiscalitalocale/nuova_imu/download_lib.php?key=0900f23080795784&nome=8625_DIMUNIC-01pe25l846d.pdf",
        "key_documentum": "0900f23080795784"
      }
    ]
  },
  {
    "url_pagina": "https://www1.finanze.gov.it/finanze2/dipartimentopolitichefiscali/fiscalitalocale/nuova_imu/risultato.htm?lista=1&r=1&pagina=abruzzo.htm&cm=&pr=PE&anno=2025&cc=L922",
    "comune": "VILLA CELIERA",
    "codice_catastale": "L922",
    "provincia": "PE",
    "delibere": [
      {
        "anno_riferimento": 2025,
        "num_delibera": "22",
        "data_delibera": "16-12-2024",
        "data_pubblicazione": "07-02-2025",
        "codice_tributo": "IMU",
        "note": "",
        "nome_prospetto": "7525_DIMUNIC-01pe25l922d.pdf",
        "link_prospetto": "https://www1.finanze.gov.it/finanze2/dipartimentopolitichefiscali/fiscalitalocale/nuova_imu/download_lib.php?key=0900f23080776bf1&nome=7525_DIMUNIC-01pe25l922d.pdf",
        "key_documentum": "0900f23080776bf1"
      }
    ]
  }
]