[
  {
    "comune": "ALBI",
    "codice_catastale": "A155",
    "motivo": "Nessun prospetto trovato"
  },
  {
    "comune": "CARDINALE",
    "codice_catastale": "B758",
    "motivo": "Nessun prospetto trovato"
  },
  {
    "comune": "MAGISANO",
    "codice_catastale": "E806",
    "motivo": "Nessun prospetto trovato"
  },
  {
    "comune": "SANTA CATERINA DELLO IONIO",
    "codice_catastale": "I170",
    "motivo": "Nessun prospetto trovato"
  },
  {
    "comune": "SELLIA",
    "codice_catastale": "I589",
    "motivo": "Nessun prospetto trovato"
  },
  {
    "comune": "SOVERIA MANNELLI",
    "codice_catastale": "I874",
    "motivo": "Nessun prospetto trovato"
  }
]