[
  {
    "url_pagina": "https://www1.finanze.gov.it/finanze2/dipartimentopolitichefiscali/fiscalitalocale/nuova_imu/risultato.htm?lista=1&r=1&pagina=molise.htm&cm=&pr=CB&anno=2025&cc=A050",
    "comune": "ACQUAVIVA COLLECROCE",
    "codice_catastale": "A050",
    "provincia": "CB",
    "delibere": [
      {
        "anno_riferimento": 2025,
        "num_delibera": "8",
        "data_delibera": "25-02-2025",
        "data_pubblicazione": "07-05-2025",
        "codice_tributo": "IMU",
        "note": "",
        "nome_prospetto": "7280_DIMUNIC-11cb25a050d.pdf",
        "link_prospetto": "https://www1.finanze.gov.it/finanze2/dipartimentopolitichefiscali/fiscalitalocale/nuova_imu/download_lib.php?key=0900f230807ed084&nome=7280_DIMUNIC-11cb25a050d.pdf",
        "key_documentum": "0900f230807ed084"
      }
    ]
  },
  {
    "url_pagina": "https://www1.finanze.gov.it/finanze2/dipartimentopolitichefiscali/fiscalitalocale/nuova_imu/risultato.htm?lista=1&r=1&pagina=molise.htm&cm=&pr=CB&anno=2025&cc=A616",
    "comune": "BARANELLO",
    "codice_catastale": "A616",
    "provincia": "CB",
    "delibere": [
      {
        "anno_riferimento": 2025,
        "num_delibera": "35",
        "data_delibera": "27-12-2024",
        "data_pubblicazione": "03-02-2025",
        "codice_tributo": "IMU",
        "note": "",
        "nome_prospetto": "3877_DIMUNIC-11cb25a616d.pdf",
        "link_prospetto": "https://www1.finanze.gov.it/finanze2/dipartimentopolitichefiscali/fiscalitalocale/nuova_imu/download_lib.php?key=0900f230807671f9&nome=3877_DIMUNIC-11cb25a616d.pdf",
        "key_documentum": "0900f230807671f9"
      }
    ]
  },
  {
    "url_pagina": "https://www1.finanze.gov.it/finanze2/dipartimentopolitichefiscali/fiscalitalocale/nuova_imu/risultato.htm?lista=1&r=1&pagina=molise.htm&cm=&pr=CB&anno=2025&cc=A930",
    "comune": "BOJANO",
    "codice_catastale": "A930",
    "provincia": "CB",
    "delibere": [
      {
        "anno_riferimento": 2025,
        "num_delibera": "4",
        "data_delibera": "24-02-2025",
        "data_pubblicazione": "13-03-2025",
        "codice_tributo": "IMU",
        "note": "",
        "nome_prospetto": "7318_DIMUNIC-11cb25a930d.pdf",
        "link_prospetto": "https://www1.finanze.gov.it/finanze2/dipartimentopolitichefiscali/fiscalitalocale/nuova_imu/download_lib.php?key=0900f230807a786b&nome=7318_DIMUNIC-11cb25a930d.pdf",
        "key_documentum": "0900f230807a786b"
      }
    ]
  },
  {
    "url_pagina": "https://www1.finanze.gov.it/finanze2/dipartimentopolitichefiscali/fiscalitalocale/nuova_imu/risultato.htm?lista=1&r=1&pagina=molise.htm&cm=&pr=CB&anno=2025&cc=A971",
    "comune": "BONEFRO",
    "codice_catastale": "A971",
    "provincia": "CB",
    "delibere": [
      {
        "anno_riferimento": 2025,
        "num_delibera": "18",
        "data_delibera": "30-12-2024",
        "data_pubblicazione": "09-01-2025",
        "codice_tributo": "IMU",
        "note": "",
        "nome_prospetto": "5892_DIMUNIC-11cb25a971d.pdf",
        "link_prospetto": "https://www1.finanze.gov.it/finanze2/dipartimentopolitichefiscali/fiscalitalocale/nuova_imu/download_lib.php?key=0900f2308074efdb&nome=5892_DIMUNIC-11cb25a971d.pdf",
        "key_documentum": "0900f2308074efdb"
      }
    ]
  },
  {
    "url_pagina": "https://www1.finanze.gov.it/finanze2/dipartimentopolitichefiscali/fiscalitalocale/nuova_imu/risultato.htm?lista=1&r=1&pagina=molise.htm&cm=&pr=CB&anno=2025&cc=B295",
    "comune": "BUSSO",
    "codice_catastale": "B295",
    "provincia": "CB",
    "delibere": [
      {
        "anno_riferimento": 2025,
        "num_delibera": "27",
        "data_delibera": "18-12-2024",
        "data_pubblicazione": "30-12-2024",
        "codice_tributo": "IMU",
        "note": "",
        "nome_prospetto": "2477_DIMUNIC-11cb25b295d.pdf",
        "link_prospetto": "https://www1.finanze.gov.it/finanze2/dipartimentopolitichefiscali/fiscalitalocale/nuova_imu/download_lib.php?key=0900f230807474d4&nome=2477_DIMUNIC-11cb25b295d.pdf",
        "key_documentum": "0900f230807474d4"
      }
    ]
  },
  {
    "url_pagina": "https://www1.finanze.gov.it/finanze2/dipartimentopolitichefiscali/fiscalitalocale/nuova_imu/risultato.htm?lista=1&r=1&pagina=molise.htm&cm=&pr=CB&anno=2025&cc=B519",
    "comune": "CAMPOBASSO",
    "codice_catastale": "B519",
    "provincia": "CB",
    "delibere": [
      {
        "anno_riferimento": 2025,
        "num_delibera": "39",
        "data_delibera": "20-12-2024",
        "data_pubblicazione": "03-02-2025",
        "codice_tributo": "IMU",
        "note": "",
        "nome_prospetto": "3987_DIMUNIC-11cb25b519d.pdf",
        "link_prospetto": "https://www1.finanze.gov.it/finanze2/dipartimentopolitichefiscali/fiscalitalocale/nuova_imu/download_lib.php?key=0900f23080764f03&nome=3987_DIMUNIC-11cb25b519d.pdf",
        "key_documentum": "0900f23080764f03"
      }
    ]
  },
  {
    "url_pagina": "https://www1.finanze.gov.it/finanze2/dipartimentopolitichefiscali/fiscalitalocale/nuova_imu/risultato.htm?lista=1&r=1&pagina=molise.htm&cm=&pr=CB&anno=2025&cc=B522",
    "comune": "CAMPOCHIARO",
    "codice_catastale": "B522",
    "provincia": "CB",
    "delibere": [
      {
        "anno_riferimento": 2025,
        "num_delibera": "16",
        "data_delibera": "18-12-2024",
        "data_pubblicazione": "25-02-2025",
        "codice_tributo": "IMU",
        "note": "",
        "nome_prospetto": "3612_DIMUNIC-11cb25b522d.pdf",
        "link_prospetto": "https://www1.finanze.gov.it/finanze2/dipartimentopolitichefiscali/fiscalitalocale/nuova_imu/download_lib.php?key=0900f23080792cbd&nome=3612_DIMUNIC-11cb25b522d.pdf",
        "key_documentum": "0900f23080792cbd"
      }
    ]
  },
  {
    "url_pagina": "https://www1.finanze.gov.it/finanze2/dipartimentopolitichefiscali/fiscalitalocale/nuova_imu/risultato.htm?lista=1&r=1&pagina=molise.htm&cm=&pr=CB&anno=2025&cc=B528",
    "comune": "CAMPODIPIETRA",
    "codice_catastale": "B528",
    "provincia": "CB",
    "delibere": [
      {
        "anno_riferimento": 2025,
        "num_delibera": "58",
        "data_delibera": "30-12-2024",
        "data_pubblicazione": "10-02-2025",
        "codice_tributo": "IMU",
        "note": "",
        "nome_prospetto": "903_DIMUNIC-11cb25b528d.pdf",
        "link_prospetto": "https://www1.finanze.gov.it/finanze2/dipartimentopolitichefiscali/fiscalitalocale/nuova_imu/download_lib.php?key=0900f2308077b3c7&nome=903_DIMUNIC-11cb25b528d.pdf",
        "key_documentum": "0900f2308077b3c7"
      }
    ]
  },
  {
    "url_pagina": "https://www1.finanze.gov.it/finanze2/dipartimentopolitichefiscali/fiscalitalocale/nuova_imu/risultato.htm?lista=1&r=1&pagina=molise.htm&cm=&pr=CB&anno=2025&cc=B544",
    "comune": "CAMPOLIETO",
    "codice_catastale": "B544",
    "provincia": "CB",
    "delibere": [
      {
        "anno_riferimento": 2025,
        "num_delibera": "21",
        "data_delibera": "28-12-2024",
        "data_pubblicazione": "24-02-2025",
        "codice_tributo": "IMU",
        "note": "",
        "nome_prospetto": "6579_DIMUNIC-11cb25b544d.pdf",
        "link_prospetto": "https://www1.finanze.gov.it/finanze2/dipartimentopolitichefiscali/fiscalitalocale/nuova_imu/download_lib.php?key=0900f2308077cf72&nome=6579_DIMUNIC-11cb25b544d.pdf",
        "key_documentum": "0900f2308077cf72"
      },
      {
        "anno_riferimento": 2025,
        "num_delibera": "21",
        "data_delibera": "28-12-2024",
        "data_pubblicazione": "25-02-2025",
        "codice_tributo": "IMU",
        "note": "ERRATA CORRIGE PER CORREZIONE DATI PROSPETTO",
        "nome_prospetto": "8413_DIMUNIC-11cb25b544d.pdf",
        "link_prospetto": "https://www1.finanze.gov.it/finanze2/dipartimentopolitichefiscali/fiscalitalocale/nuova_imu/download_lib.php?key=0900f2308078fce7&nome=8413_DIMUNIC-11cb25b544d.pdf",
        "key_documentum": "0900f2308078fce7"
      }
    ]
  },
  {
    "url_pagina": "https://www1.finanze.gov.it/finanze2/dipartimentopolitichefiscali/fiscalitalocale/nuova_imu/risultato.htm?lista=1&r=1&pagina=molise.htm&cm=&pr=CB&anno=2025&cc=B550",
    "comune": "CAMPOMARINO",
    "codice_catastale": "B550",
    "provincia": "CB",
    "delibere": [
      {
        "anno_riferimento": 2025,
        "num_delibera": "3",
        "data_delibera": "24-02-2025",
        "data_pubblicazione": "28-02-2025",
        "codice_tributo": "IMU",
        "note": "",
        "nome_prospetto": "3178_DIMUNIC-11cb25b550d.pdf",
        "link_prospetto": "https://www1.finanze.gov.it/finanze2/dipartimentopolitichefiscali/fiscalitalocale/nuova_imu/download_lib.php?key=0900f2308079796f&nome=3178_DIMUNIC-11cb25b550d.pdf",
        "key_documentum": "0900f2308079796f"
      },
      {
        "anno_riferimento": 2025,
        "num_delibera": "3",
        "data_delibera": "24-02-2025",
        "data_pubblicazione": "09-05-2025",
        "codice_tributo": "IMU",
        "note": "ERRATA CORRIGE PER CORREZIONE DATI PROSPETTO",
        "nome_prospetto": "9547_DIMUNIC-11cb25b550d.pdf",
        "link_prospetto": "https://www1.finanze.gov.it/finanze2/dipartimentopolitichefiscali/fiscalitalocale/nuova_imu/download_lib.php?key=0900f230807f0ab2&nome=9547_DIMUNIC-11cb25b550d.pdf",
        "key_documentum": "0900f230807f0ab2"
      }
    ]
  },
  {
    "url_pagina": "https://www1.finanze.gov.it/finanze2/dipartimentopolitichefiscali/fiscalitalocale/nuova_imu/risultato.htm?lista=1&r=1&pagina=molise.htm&cm=&pr=CB&anno=2025&cc=B858",
    "comune": "CASACALENDA",
    "codice_catastale": "B858",
    "provincia": "CB",
    "delibere": [
      {
        "anno_riferimento": 2025,
        "num_delibera": "9",
        "data_delibera": "28-02-2025",
        "data_pubblicazione": "31-03-2025",
        "codice_tributo": "IMU",
        "note": "",
        "nome_prospetto": "7736_DIMUNIC-11cb25b858d.pdf",
        "link_prospetto": "https://www1.finanze.gov.it/finanze2/dipartimentopolitichefiscali/fiscalitalocale/nuova_imu/download_lib.php?key=0900f230807be048&nome=7736_DIMUNIC-11cb25b858d.pdf",
        "key_documentum": "0900f230807be048"
      }
    ]
  },
  {
    "url_pagina": "https://www1.finanze.gov.it/finanze2/dipartimentopolitichefiscali/fiscalitalocale/nuova_imu/risultato.htm?lista=1&r=1&pagina=molise.htm&cm=&pr=CB&anno=2025&cc=B871",
    "comune": "CASALCIPRANO",
    "codice_catastale": "B871",
    "provincia": "CB",
    "delibere": [
      {
        "anno_riferimento": 2025,
        "num_delibera": "4",
        "data_delibera": "11-03-2025",
        "data_pubblicazione": "13-03-2025",
        "codice_tributo": "IMU",
        "note": "",
        "nome_prospetto": "8342_DIMUNIC-11cb25b871d.pdf",
        "link_prospetto": "https://www1.finanze.gov.it/finanze2/dipartimentopolitichefiscali/fiscalitalocale/nuova_imu/download_lib.php?key=0900f230807a72d7&nome=8342_DIMUNIC-11cb25b871d.pdf",
        "key_documentum": "0900f230807a72d7"
      }
    ]
  },
  {
    "url_pagina": "https://www1.finanze.gov.it/finanze2/dipartimentopolitichefiscali/fiscalitalocale/nuova_imu/risultato.htm?lista=1&r=1&pagina=molise.htm&cm=&pr=CB&anno=2025&cc=C066",
    "comune": "CASTELBOTTACCIO",
    "codice_catastale": "C066",
    "provincia": "CB",
    "delibere": [
      {
        "anno_riferimento": 2025,
        "num_delibera": "12",
        "data_delibera": "19-12-2024",
        "data_pubblicazione": "28-02-2025",
        "codice_tributo": "IMU",
        "note": "",
        "nome_prospetto": "5631_DIMUNIC-11cb25c066d.pdf",
        "link_prospetto": "https://www1.finanze.gov.it/finanze2/dipartimentopolitichefiscali/fiscalitalocale/nuova_imu/download_lib.php?key=0900f23080797941&nome=5631_DIMUNIC-11cb25c066d.pdf",
        "key_documentum": "0900f23080797941"
      }
    ]
  },
  {
    "url_pagina": "https://www1.finanze.gov.it/finanze2/dipartimentopolitichefiscali/fiscalitalocale/nuova_imu/risultato.htm?lista=1&r=1&pagina=molise.htm&cm=&pr=CB&anno=2025&cc=C175",
    "comune": "CASTELLINO DEL BIFERNO",
    "codice_catastale": "C175",
    "provincia": "CB",
    "delibere": [
      {
        "anno_riferimento": 2025,
        "num_delibera": "23",
        "data_delibera": "19-12-2024",
        "data_pubblicazione": "14-01-2025",
        "codice_tributo": "IMU",
        "note": "",
        "nome_prospetto": "6029_DIMUNIC-11cb25c175d.pdf",
        "link_prospetto": "https://www1.finanze.gov.it/finanze2/dipartimentopolitichefiscali/fiscalitalocale/nuova_imu/download_lib.php?key=0900f23080756626&nome=6029_DIMUNIC-11cb25c175d.pdf",
        "key_documentum": "0900f23080756626"
      }
    ]
  },
  {
    "url_pagina": "https://www1.finanze.gov.it/finanze2/dipartimentopolitichefiscali/fiscalitalocale/nuova_imu/risultato.htm?lista=1&r=1&pagina=molise.htm&cm=&pr=CB&anno=2025&cc=C197",
    "comune": "CASTELMAURO",
    "codice_catastale": "C197",
    "provincia": "CB",
    "delibere": [
      {
        "anno_riferimento": 2025,
        "num_delibera": "9",
        "data_delibera": "27-02-2025",
        "data_pubblicazione": "28-02-2025",
        "codice_tributo": "IMU",
        "note": "",
        "nome_prospetto": "7920_DIMUNIC-11cb25c197d.pdf",
        "link_prospetto": "https://www1.finanze.gov.it/finanze2/dipartimentopolitichefiscali/fiscalitalocale/nuova_imu/download_lib.php?key=0900f23080796f0b&nome=7920_DIMUNIC-11cb25c197d.pdf",
        "key_documentum": "0900f23080796f0b"
      }
    ]
  },
  {
    "url_pagina": "https://www1.finanze.gov.it/finanze2/dipartimentopolitichefiscali/fiscalitalocale/nuova_imu/risultato.htm?lista=1&r=1&pagina=molise.htm&cm=&pr=CB&anno=2025&cc=C346",
    "comune": "CASTROPIGNANO",
    "codice_catastale": "C346",
    "provincia": "CB",
    "delibere": [
      {
        "anno_riferimento": 2025,
        "num_delibera": "17",
        "data_delibera": "13-03-2025",
        "data_pubblicazione": "18-08-2025",
        "codice_tributo": "IMU",
        "note": "",
        "nome_prospetto": "3138_DIMUNIC-11cb25c346d.pdf",
        "link_prospetto": "https://www1.finanze.gov.it/finanze2/dipartimentopolitichefiscali/fiscalitalocale/nuova_imu/download_lib.php?key=0900f230808e0939&nome=3138_DIMUNIC-11cb25c346d.pdf",
        "key_documentum": "0900f230808e0939"
      }
    ]
  },
  {
    "url_pagina": "https://www1.finanze.gov.it/finanze2/dipartimentopolitichefiscali/fiscalitalocale/nuova_imu/risultato.htm?lista=1&r=1&pagina=molise.htm&cm=&pr=CB&anno=2025&cc=C486",
    "comune": "CERCEMAGGIORE",
    "codice_catastale": "C486",
    "provincia": "CB",
    "delibere": [
      {
        "anno_riferimento": 2025,
        "num_delibera": "30",
        "data_delibera": "18-12-2024",
        "data_pubblicazione": "03-02-2025",
        "codice_tributo": "IMU",
        "note": "",
        "nome_prospetto": "2339_DIMUNIC-11cb25c486d.pdf",
        "link_prospetto": "https://www1.finanze.gov.it/finanze2/dipartimentopolitichefiscali/fiscalitalocale/nuova_imu/download_lib.php?key=0900f23080768b40&nome=2339_DIMUNIC-11cb25c486d.pdf",
        "key_documentum": "0900f23080768b40"
      }
    ]
  },
  {
    "url_pagina": "https://www1.finanze.gov.it/finanze2/dipartimentopolitichefiscali/fiscalitalocale/nuova_imu/risultato.htm?lista=1&r=1&pagina=molise.htm&cm=&pr=CB&anno=2025&cc=C488",
    "comune": "CERCEPICCOLA",
    "codice_catastale": "C488",
    "provincia": "CB",
    "delibere": [
      {
        "anno_riferimento": 2025,
        "num_delibera": "24",
        "data_delibera": "18-12-2024",
        "data_pubblicazione": "14-01-2025",
        "codice_tributo": "IMU",
        "note": "",
        "nome_prospetto": "1661_DIMUNIC-11cb25c488d.pdf",
        "link_prospetto": "https://www1.finanze.gov.it/finanze2/dipartimentopolitichefiscali/fiscalitalocale/nuova_imu/download_lib.php?key=0900f23080754d4e&nome=1661_DIMUNIC-11cb25c488d.pdf",
        "key_documentum": "0900f23080754d4e"
      }
    ]
  },
  {
    "url_pagina": "https://www1.finanze.gov.it/finanze2/dipartimentopolitichefiscali/fiscalitalocale/nuova_imu/risultato.htm?lista=1&r=1&pagina=molise.htm&cm=&pr=CB&anno=2025&cc=C764",
    "comune": "CIVITACAMPOMARANO",
    "codice_catastale": "C764",
    "provincia": "CB",
    "delibere": [
      {
        "anno_riferimento": 2025,
        "num_delibera": "24",
        "data_delibera": "19-12-2024",
        "data_pubblicazione": "03-01-2025",
        "codice_tributo": "IMU",
        "note": "",
        "nome_prospetto": "2968_DIMUNIC-11cb25c764d.pdf",
        "link_prospetto": "https://www1.finanze.gov.it/finanze2/dipartimentopolitichefiscali/fiscalitalocale/nuova_imu/download_lib.php?key=0900f2308074cf87&nome=2968_DIMUNIC-11cb25c764d.pdf",
        "key_documentum": "0900f2308074cf87"
      }
    ]
  },
  {
    "url_pagina": "https://www1.finanze.gov.it/finanze2/dipartimentopolitichefiscali/fiscalitalocale/nuova_imu/risultato.htm?lista=1&r=1&pagina=molise.htm&cm=&pr=CB&anno=2025&cc=C854",
    "comune": "COLLE D'ANCHISE",
    "codice_catastale": "C854",
    "provincia": "CB",
    "delibere": [
      {
        "anno_riferimento": 2025,
        "num_delibera": "34",
        "data_delibera": "30-12-2024",
        "data_pubblicazione": "27-02-2025",
        "codice_tributo": "IMU",
        "note": "",
        "nome_prospetto": "8659_DIMUNIC-11cb25c854d.pdf",
        "link_prospetto": "https://www1.finanze.gov.it/finanze2/dipartimentopolitichefiscali/fiscalitalocale/nuova_imu/download_lib.php?key=0900f23080796003&nome=8659_DIMUNIC-11cb25c854d.pdf",
        "key_documentum": "0900f23080796003"
      }
    ]
  },
  {
    "url_pagina": "https://www1.finanze.gov.it/finanze2/dipartimentopolitichefiscali/fiscalitalocale/nuova_imu/risultato.htm?lista=1&r=1&pagina=molise.htm&cm=&pr=CB&anno=2025&cc=C875",
    "comune": "COLLETORTO",
    "codice_catastale": "C875",
    "provincia": "CB",
    "delibere": [
      {
        "anno_riferimento": 2025,
        "num_delibera": "30",
        "data_delibera": "27-12-2024",
        "data_pubblicazione": "09-01-2025",
        "codice_tributo": "IMU",
        "note": "",
        "nome_prospetto": "5054_DIMUNIC-11cb25c875d.pdf",
        "link_prospetto": "https://www1.finanze.gov.it/finanze2/dipartimentopolitichefiscali/fiscalitalocale/nuova_imu/download_lib.php?key=0900f2308074f21e&nome=5054_DIMUNIC-11cb25c875d.pdf",
        "key_documentum": "0900f2308074f21e"
      }
    ]
  },
  {
    "url_pagina": "https://www1.finanze.gov.it/finanze2/dipartimentopolitichefiscali/fiscalitalocale/nuova_imu/risultato.htm?lista=1&r=1&pagina=molise.htm&cm=&pr=CB&anno=2025&cc=C772",
    "comune": "DURONIA",
    "codice_catastale": "C772",
    "provincia": "CB",
    "delibere": [
      {
        "anno_riferimento": 2025,
        "num_delibera": "20",
        "data_delibera": "14-12-2024",
        "data_pubblicazione": "31-12-2024",
        "codice_tributo": "IMU",
        "note": "",
        "nome_prospetto": "4813_DIMUNIC-11cb25c772d.pdf",
        "link_prospetto": "https://www1.finanze.gov.it/finanze2/dipartimentopolitichefiscali/fiscalitalocale/nuova_imu/download_lib.php?key=0900f2308074935c&nome=4813_DIMUNIC-11cb25c772d.pdf",
        "key_documentum": "0900f2308074935c"
      }
    ]
  },
  {
    "url_pagina": "https://www1.finanze.gov.it/finanze2/dipartimentopolitichefiscali/fiscalitalocale/nuova_imu/risultato.htm?lista=1&r=1&pagina=molise.htm&cm=&pr=CB&anno=2025&cc=D550",
    "comune": "FERRAZZANO",
    "codice_catastale": "D550",
    "provincia": "CB",
    "delibere": [
      {
        "anno_riferimento": 2025,
        "num_delibera": "30",
        "data_delibera": "27-12-2024",
        "data_pubblicazione": "26-02-2025",
        "codice_tributo": "IMU",
        "note": "",
        "nome_prospetto": "6482_DIMUNIC-11cb25d550d.pdf",
        "link_prospetto": "https://www1.finanze.gov.it/finanze2/dipartimentopolitichefiscali/fiscalitalocale/nuova_imu/download_lib.php?key=0900f2308079425d&nome=6482_DIMUNIC-11cb25d550d.pdf",
        "key_documentum": "0900f2308079425d"
      }
    ]
  },
  {
    "url_pagina": "https://www1.finanze.gov.it/finanze2/dipartimentopolitichefiscali/fiscalitalocale/nuova_imu/risultato.htm?lista=1&r=1&pagina=molise.htm&cm=&pr=CB&anno=2025&cc=D737",
    "comune": "FOSSALTO",
    "codice_catastale": "D737",
    "provincia": "CB",
    "delibere": [
      {
        "anno_riferimento": 2025,
        "num_delibera": "5",
        "data_delibera": "13-03-2025",
        "data_pubblicazione": "31-03-2025",
        "codice_tributo": "IMU",
        "note": "",
        "nome_prospetto": "8081_DIMUNIC-11cb25d737d.pdf",
        "link_prospetto": "https://www1.finanze.gov.it/finanze2/dipartimentopolitichefiscali/fiscalitalocale/nuova_imu/download_lib.php?key=0900f230807be601&nome=8081_DIMUNIC-11cb25d737d.pdf",
        "key_documentum": "0900f230807be601"
      }
    ]
  },
  {
    "url_pagina": "https://www1.finanze.gov.it/finanze2/dipartimentopolitichefiscali/fiscalitalocale/nuova_imu/risultato.htm?lista=1&r=1&pagina=molise.htm&cm=&pr=CB&anno=2025&cc=D896",
    "comune": "GAMBATESA",
    "codice_catastale": "D896",
    "provincia": "CB",
    "delibere": [
      {
        "anno_riferimento": 2025,
        "num_delibera": "29",
        "data_delibera": "30-12-2024",
        "data_pubblicazione": "03-02-2025",
        "codice_tributo": "IMU",
        "note": "",
        "nome_prospetto": "1332_DIMUNIC-11cb25d896d.pdf",
        "link_prospetto": "https://www1.finanze.gov.it/finanze2/dipartimentopolitichefiscali/fiscalitalocale/nuova_imu/download_lib.php?key=0900f2308076b1f0&nome=1332_DIMUNIC-11cb25d896d.pdf",
        "key_documentum": "0900f2308076b1f0"
      }
    ]
  },
  {
    "url_pagina": "https://www1.finanze.gov.it/finanze2/dipartimentopolitichefiscali/fiscalitalocale/nuova_imu/risultato.htm?lista=1&r=1&pagina=molise.htm&cm=&pr=CB&anno=2025&cc=E030",
    "comune": "GILDONE",
    "codice_catastale": "E030",
    "provincia": "CB",
    "delibere": [
      {
        "anno_riferimento": 2025,
        "num_delibera": "45",
        "data_delibera": "19-12-2024",
        "data_pubblicazione": "04-02-2025",
        "codice_tributo": "IMU",
        "note": "",
        "nome_prospetto": "4403_DIMUNIC-11cb25e030d.pdf",
        "link_prospetto": "https://www1.finanze.gov.it/finanze2/dipartimentopolitichefiscali/fiscalitalocale/nuova_imu/download_lib.php?key=0900f2308076088f&nome=4403_DIMUNIC-11cb25e030d.pdf",
        "key_documentum": "0900f2308076088f"
      }
    ]
  },
  {
    "url_pagina": "https://www1.finanze.gov.it/finanze2/dipartimentopolitichefiscali/fiscalitalocale/nuova_imu/risultato.htm?lista=1&r=1&pagina=molise.htm&cm=&pr=CB&anno=2025&cc=E244",
    "comune": "GUARDIALFIERA",
    "codice_catastale": "E244",
    "provincia": "CB",
    "delibere": [
      {
        "anno_riferimento": 2025,
        "num_delibera": "37",
        "data_delibera": "20-12-2024",
        "data_pubblicazione": "10-01-2025",
        "codice_tributo": "IMU",
        "note": "",
        "nome_prospetto": "5893_DIMUNIC-11cb25e244d.pdf",
        "link_prospetto": "https://www1.finanze.gov.it/finanze2/dipartimentopolitichefiscali/fiscalitalocale/nuova_imu/download_lib.php?key=0900f230807523f5&nome=5893_DIMUNIC-11cb25e244d.pdf",
        "key_documentum": "0900f230807523f5"
      }
    ]
  },
  {
    "url_pagina": "https://www1.finanze.gov.it/finanze2/dipartimentopolitichefiscali/fiscalitalocale/nuova_imu/risultato.htm?lista=1&r=1&pagina=molise.htm&cm=&pr=CB&anno=2025&cc=E248",
    "comune": "GUARDIAREGIA",
    "codice_catastale": "E248",
    "provincia": "CB",
    "delibere": [
      {
        "anno_riferimento": 2025,
        "num_delibera": "30",
        "data_delibera": "19-12-2024",
        "data_pubblicazione": "03-02-2025",
        "codice_tributo": "IMU",
        "note": "",
        "nome_prospetto": "401_DIMUNIC-11cb25e248d.pdf",
        "link_prospetto": "https://www1.finanze.gov.it/finanze2/dipartimentopolitichefiscali/fiscalitalocale/nuova_imu/download_lib.php?key=0900f2308075e4f9&nome=401_DIMUNIC-11cb25e248d.pdf",
        "key_documentum": "0900f2308075e4f9"
      }
    ]
  },
  {
    "url_pagina": "https://www1.finanze.gov.it/finanze2/dipartimentopolitichefiscali/fiscalitalocale/nuova_imu/risultato.htm?lista=1&r=1&pagina=molise.htm&cm=&pr=CB&anno=2025&cc=E259",
    "comune": "GUGLIONESI",
    "codice_catastale": "E259",
    "provincia": "CB",
    "delibere": [
      {
        "anno_riferimento": 2025,
        "num_delibera": "24",
        "data_delibera": "17-12-2024",
        "data_pubblicazione": "19-12-2024",
        "codice_tributo": "IMU",
        "note": "",
        "nome_prospetto": "5469_DIMUNIC-11cb25e259d.pdf",
        "link_prospetto": "https://www1.finanze.gov.it/finanze2/dipartimentopolitichefiscali/fiscalitalocale/nuova_imu/download_lib.php?key=0900f2308073fe0c&nome=5469_DIMUNIC-11cb25e259d.pdf",
        "key_documentum": "0900f2308073fe0c"
      }
    ]
  },
  {
    "url_pagina": "https://www1.finanze.gov.it/finanze2/dipartimentopolitichefiscali/fiscalitalocale/nuova_imu/risultato.htm?lista=1&r=1&pagina=molise.htm&cm=&pr=CB&anno=2025&cc=E381",
    "comune": "JELSI",
    "codice_catastale": "E381",
    "provincia": "CB",
    "delibere": [
      {
        "anno_riferimento": 2025,
        "num_delibera": "27",
        "data_delibera": "19-12-2024",
        "data_pubblicazione": "26-02-2025",
        "codice_tributo": "IMU",
        "note": "",
        "nome_prospetto": "2599_DIMUNIC-11cb25e381d.pdf",
        "link_prospetto": "https://www1.finanze.gov.it/finanze2/dipartimentopolitichefiscali/fiscalitalocale/nuova_imu/download_lib.php?key=0900f2308076b8ce&nome=2599_DIMUNIC-11cb25e381d.pdf",
        "key_documentum": "0900f2308076b8ce"
      }
    ]
  },
  {
    "url_pagina": "https://www1.finanze.gov.it/finanze2/dipartimentopolitichefiscali/fiscalitalocale/nuova_imu/risultato.htm?lista=1&r=1&pagina=molise.htm&cm=&pr=CB&anno=2025&cc=E456",
    "comune": "LARINO",
    "codice_catastale": "E456",
    "provincia": "CB",
    "delibere": [
      {
        "anno_riferimento": 2025,
        "num_delibera": "12",
        "data_delibera": "27-02-2025",
        "data_pubblicazione": "12-03-2025",
        "codice_tributo": "IMU",
        "note": "",
        "nome_prospetto": "7222_DIMUNIC-11cb25e456d.pdf",
        "link_prospetto": "https://www1.finanze.gov.it/finanze2/dipartimentopolitichefiscali/fiscalitalocale/nuova_imu/download_lib.php?key=0900f230807a60b6&nome=7222_DIMUNIC-11cb25e456d.pdf",
        "key_documentum": "0900f230807a60b6"
      }
    ]
  },
  {
    "url_pagina": "https://www1.finanze.gov.it/finanze2/dipartimentopolitichefiscali/fiscalitalocale/nuova_imu/risultato.htm?lista=1&r=1&pagina=molise.htm&cm=&pr=CB&anno=2025&cc=E599",
    "comune": "LIMOSANO",
    "codice_catastale": "E599",
    "provincia": "CB",
    "delibere": [
      {
        "anno_riferimento": 2025,
        "num_delibera": "3",
        "data_delibera": "26-02-2025",
        "data_pubblicazione": "28-02-2025",
        "codice_tributo": "IMU",
        "note": "",
        "nome_prospetto": "7609_DIMUNIC-11cb25e599d.pdf",
        "link_prospetto": "https://www1.finanze.gov.it/finanze2/dipartimentopolitichefiscali/fiscalitalocale/nuova_imu/download_lib.php?key=0900f230807979fe&nome=7609_DIMUNIC-11cb25e599d.pdf",
        "key_documentum": "0900f230807979fe"
      }
    ]
  },
  {
    "url_pagina": "https://www1.finanze.gov.it/finanze2/dipartimentopolitichefiscali/fiscalitalocale/nuova_imu/risultato.htm?lista=1&r=1&pagina=molise.htm&cm=&pr=CB&anno=2025&cc=E722",
    "comune": "LUCITO",
    "codice_catastale": "E722",
    "provincia": "CB",
    "delibere": [
      {
        "anno_riferimento": 2025,
        "num_delibera": "27",
        "data_delibera": "17-12-2024",
        "data_pubblicazione": "03-01-2025",
        "codice_tributo": "IMU",
        "note": "",
        "nome_prospetto": "4943_DIMUNIC-11cb25e722d.pdf",
        "link_prospetto": "https://www1.finanze.gov.it/finanze2/dipartimentopolitichefiscali/fiscalitalocale/nuova_imu/download_lib.php?key=0900f2308074d645&nome=4943_DIMUNIC-11cb25e722d.pdf",
        "key_documentum": "0900f2308074d645"
      }
    ]
  },
  {
    "url_pagina": "https://www1.finanze.gov.it/finanze2/dipartimentopolitichefiscali/fiscalitalocale/nuova_imu/risultato.htm?lista=1&r=1&pagina=molise.htm&cm=&pr=CB&anno=2025&cc=E780",
    "comune": "MACCHIA VALFORTORE",
    "codice_catastale": "E780",
    "provincia": "CB",
    "delibere": [
      {
        "anno_riferimento": 2025,
        "num_delibera": "22",
        "data_delibera": "27-12-2024",
        "data_pubblicazione": "03-03-2025",
        "codice_tributo": "IMU",
        "note": "",
        "nome_prospetto": "6580_DIMUNIC-11cb25e780d.pdf",
        "link_prospetto": "https://www1.finanze.gov.it/finanze2/dipartimentopolitichefiscali/fiscalitalocale/nuova_imu/download_lib.php?key=0900f230807983ac&nome=6580_DIMUNIC-11cb25e780d.pdf",
        "key_documentum": "0900f230807983ac"
      }
    ]
  },
  {
    "url_pagina": "https://www1.finanze.gov.it/finanze2/dipartimentopolitichefiscali/fiscalitalocale/nuova_imu/risultato.htm?lista=1&r=1&pagina=molise.htm&cm=&pr=CB&anno=2025&cc=E799",
    "comune": "MAFALDA",
    "codice_catastale": "E799",
    "provincia": "CB",
    "delibere": [
      {
        "anno_riferimento": 2025,
        "num_delibera": "2",
        "data_delibera": "28-02-2025",
        "data_pubblicazione": "28-02-2025",
        "codice_tributo": "IMU",
        "note": "",
        "nome_prospetto": "8588_DIMUNIC-11cb25e799d.pdf",
        "link_prospetto": "https://www1.finanze.gov.it/finanze2/dipartimentopolitichefiscali/fiscalitalocale/nuova_imu/download_lib.php?key=0900f23080797b9e&nome=8588_DIMUNIC-11cb25e799d.pdf",
        "key_documentum": "0900f23080797b9e"
      }
    ]
  },
  {
    "url_pagina": "https://www1.finanze.gov.it/finanze2/dipartimentopolitichefiscali/fiscalitalocale/nuova_imu/risultato.htm?lista=1&r=1&pagina=molise.htm&cm=&pr=CB&anno=2025&cc=F055",
    "comune": "MATRICE",
    "codice_catastale": "F055",
    "provincia": "CB",
    "delibere": [
      {
        "anno_riferimento": 2025,
        "num_delibera": "22",
        "data_delibera": "10-12-2024",
        "data_pubblicazione": "19-12-2024",
        "codice_tributo": "IMU",
        "note": "",
        "nome_prospetto": "921_DIMUNIC-11cb25f055d.pdf",
        "link_prospetto": "https://www1.finanze.gov.it/finanze2/dipartimentopolitichefiscali/fiscalitalocale/nuova_imu/download_lib.php?key=0900f2308073f09e&nome=921_DIMUNIC-11cb25f055d.pdf",
        "key_documentum": "0900f2308073f09e"
      }
    ]
  },
  {
    "url_pagina": "https://www1.finanze.gov.it/finanze2/dipartimentopolitichefiscali/fiscalitalocale/nuova_imu/risultato.htm?lista=1&r=1&pagina=molise.htm&cm=&pr=CB&anno=2025&cc=F233",
    "comune": "MIRABELLO SANNITICO",
    "codice_catastale": "F233",
    "provincia": "CB",
    "delibere": [
      {
        "anno_riferimento": 2025,
        "num_delibera": "35",
        "data_delibera": "30-12-2024",
        "data_pubblicazione": "11-04-2025",
        "codice_tributo": "IMU",
        "note": "",
        "nome_prospetto": "5241_DIMUNIC-11cb25f233d.pdf",
        "link_prospetto": "https://www1.finanze.gov.it/finanze2/dipartimentopolitichefiscali/fiscalitalocale/nuova_imu/download_lib.php?key=0900f230807cec35&nome=5241_DIMUNIC-11cb25f233d.pdf",
        "key_documentum": "0900f230807cec35"
      }
    ]
  },
  {
    "url_pagina": "https://www1.finanze.gov.it/finanze2/dipartimentopolitichefiscali/fiscalitalocale/nuova_imu/risultato.htm?lista=1&r=1&pagina=molise.htm&cm=&pr=CB&anno=2025&cc=F294",
    "comune": "MOLISE",
    "codice_catastale": "F294",
    "provincia": "CB",
    "delibere": [
      {
        "anno_riferimento": 2025,
        "num_delibera": "29",
        "data_delibera": "30-12-2024",
        "data_pubblicazione": "21-02-2025",
        "codice_tributo": "IMU",
        "note": "",
        "nome_prospetto": "6351_DIMUNIC-11cb25f294d.pdf",
        "link_prospetto": "https://www1.finanze.gov.it/finanze2/dipartimentopolitichefiscali/fiscalitalocale/nuova_imu/download_lib.php?key=0900f2308078bc28&nome=6351_DIMUNIC-11cb25f294d.pdf",
        "key_documentum": "0900f2308078bc28"
      }
    ]
  },
  {
    "url_pagina": "https://www1.finanze.gov.it/finanze2/dipartimentopolitichefiscali/fiscalitalocale/nuova_imu/risultato.htm?lista=1&r=1&pagina=molise.htm&cm=&pr=CB&anno=2025&cc=F322",
    "comune": "MONACILIONI",
    "codice_catastale": "F322",
    "provincia": "CB",
    "delibere": [
      {
        "anno_riferimento": 2025,
        "num_delibera": "42",
        "data_delibera": "14-12-2024",
        "data_pubblicazione": "29-08-2025",
        "codice_tributo": "IMU",
        "note": "",
        "nome_prospetto": "4380_DIMUNIC-11cb25f322d.pdf",
        "link_prospetto": "https://www1.finanze.gov.it/finanze2/dipartimentopolitichefiscali/fiscalitalocale/nuova_imu/download_lib.php?key=0900f230808e6fb9&nome=4380_DIMUNIC-11cb25f322d.pdf",
        "key_documentum": "0900f230808e6fb9"
      }
    ]
  },
  {
    "url_pagina": "https://www1.finanze.gov.it/finanze2/dipartimentopolitichefiscali/fiscalitalocale/nuova_imu/risultato.htm?lista=1&r=1&pagina=molise.htm&cm=&pr=CB&anno=2025&cc=F475",
    "comune": "MONTECILFONE",
    "codice_catastale": "F475",
    "provincia": "CB",
    "delibere": [
      {
        "anno_riferimento": 2025,
        "num_delibera": "2",
        "data_delibera": "12-03-2025",
        "data_pubblicazione": "18-03-2025",
        "codice_tributo": "IMU",
        "note": "",
        "nome_prospetto": "8084_DIMUNIC-11cb25f475d.pdf",
        "link_prospetto": "https://www1.finanze.gov.it/finanze2/dipartimentopolitichefiscali/fiscalitalocale/nuova_imu/download_lib.php?key=0900f230807aee2a&nome=8084_DIMUNIC-11cb25f475d.pdf",
        "key_documentum": "0900f230807aee2a"
      }
    ]
  },
  {
    "url_pagina": "https://www1.finanze.gov.it/finanze2/dipartimentopolitichefiscali/fiscalitalocale/nuova_imu/risultato.htm?lista=1&r=1&pagina=molise.htm&cm=&pr=CB&anno=2025&cc=F495",
    "comune": "MONTEFALCONE NEL SANNIO",
    "codice_catastale": "F495",
    "provincia": "CB",
    "delibere": [
      {
        "anno_riferimento": 2025,
        "num_delibera": "29",
        "data_delibera": "27-12-2024",
        "data_pubblicazione": "03-02-2025",
        "codice_tributo": "IMU",
        "note": "",
        "nome_prospetto": "3482_DIMUNIC-11cb25f495d.pdf",
        "link_prospetto": "https://www1.finanze.gov.it/finanze2/dipartimentopolitichefiscali/fiscalitalocale/nuova_imu/download_lib.php?key=0900f2308076d151&nome=3482_DIMUNIC-11cb25f495d.pdf",
        "key_documentum": "0900f2308076d151"
      }
    ]
  },
  {
    "url_pagina": "https://www1.finanze.gov.it/finanze2/dipartimentopolitichefiscali/fiscalitalocale/nuova_imu/risultato.htm?lista=1&r=1&pagina=molise.htm&cm=&pr=CB&anno=2025&cc=F548",
    "comune": "MONTELONGO",
    "codice_catastale": "F548",
    "provincia": "CB",
    "delibere": [
      {
        "anno_riferimento": 2025,
        "num_delibera": "5",
        "data_delibera": "05-02-2025",
        "data_pubblicazione": "27-02-2025",
        "codice_tributo": "IMU",
        "note": "",
        "nome_prospetto": "8601_DIMUNIC-11cb25f548d.pdf",
        "link_prospetto": "https://www1.finanze.gov.it/finanze2/dipartimentopolitichefiscali/fiscalitalocale/nuova_imu/download_lib.php?key=0900f23080794ed6&nome=8601_DIMUNIC-11cb25f548d.pdf",
        "key_documentum": "0900f23080794ed6"
      }
    ]
  },
  {
    "url_pagina": "https://www1.finanze.gov.it/finanze2/dipartimentopolitichefiscali/fiscalitalocale/nuova_imu/risultato.htm?lista=1&r=1&pagina=molise.htm&cm=&pr=CB&anno=2025&cc=F569",
    "comune": "MONTEMITRO",
    "codice_catastale": "F569",
    "provincia": "CB",
    "delibere": [
      {
        "anno_riferimento": 2025,
        "num_delibera": "35",
        "data_delibera": "10-12-2024",
        "data_pubblicazione": "10-02-2025",
        "codice_tributo": "IMU",
        "note": "",
        "nome_prospetto": "3884_DIMUNIC-11cb25f569d.pdf",
        "link_prospetto": "https://www1.finanze.gov.it/finanze2/dipartimentopolitichefiscali/fiscalitalocale/nuova_imu/download_lib.php?key=0900f2308077b34b&nome=3884_DIMUNIC-11cb25f569d.pdf",
        "key_documentum": "0900f2308077b34b"
      }
    ]
  },
  {
    "url_pagina": "https://www1.finanze.gov.it/finanze2/dipartimentopolitichefiscali/fiscalitalocale/nuova_imu/risultato.htm?lista=1&r=1&pagina=molise.htm&cm=&pr=CB&anno=2025&cc=F576",
    "comune": "MONTENERO DI BISACCIA",
    "codice_catastale": "F576",
    "provincia": "CB",
    "delibere": [
      {
        "anno_riferimento": 2025,
        "num_delibera": "57",
        "data_delibera": "18-12-2024",
        "data_pubblicazione": "25-03-2025",
        "codice_tributo": "IMU",
        "note": "",
        "nome_prospetto": "5791_DIMUNIC-11cb25f576d.pdf",
        "link_prospetto": "https://www1.finanze.gov.it/finanze2/dipartimentopolitichefiscali/fiscalitalocale/nuova_imu/download_lib.php?key=0900f230807b822c&nome=5791_DIMUNIC-11cb25f576d.pdf",
        "key_documentum": "0900f230807b822c"
      }
    ]
  },
  {
    "url_pagina": "https://www1.finanze.gov.it/finanze2/dipartimentopolitichefiscali/fiscalitalocale/nuova_imu/risultato.htm?lista=1&r=1&pagina=molise.htm&cm=&pr=CB&anno=2025&cc=F689",
    "comune": "MONTORIO NEI FRENTANI",
    "codice_catastale": "F689",
    "provincia": "CB",
    "delibere": [
      {
        "anno_riferimento": 2025,
        "num_delibera": "15",
        "data_delibera": "27-12-2024",
        "data_pubblicazione": "09-01-2025",
        "codice_tributo": "IMU",
        "note": "",
        "nome_prospetto": "4107_DIMUNIC-11cb25f689d.pdf",
        "link_prospetto": "https://www1.finanze.gov.it/finanze2/dipartimentopolitichefiscali/fiscalitalocale/nuova_imu/download_lib.php?key=0900f2308074f227&nome=4107_DIMUNIC-11cb25f689d.pdf",
        "key_documentum": "0900f2308074f227"
      }
    ]
  },
  {
    "url_pagina": "https://www1.finanze.gov.it/finanze2/dipartimentopolitichefiscali/fiscalitalocale/nuova_imu/risultato.htm?lista=1&r=1&pagina=molise.htm&cm=&pr=CB&anno=2025&cc=F748",
    "comune": "MORRONE DEL SANNIO",
    "codice_catastale": "F748",
    "provincia": "CB",
    "delibere": [
      {
        "anno_riferimento": 2025,
        "num_delibera": "5",
        "data_delibera": "07-03-2025",
        "data_pubblicazione": "07-04-2025",
        "codice_tributo": "IMU",
        "note": "",
        "nome_prospetto": "8790_DIMUNIC-11cb25f748d.pdf",
        "link_prospetto": "https://www1.finanze.gov.it/finanze2/dipartimentopolitichefiscali/fiscalitalocale/nuova_imu/download_lib.php?key=0900f230807c760b&nome=8790_DIMUNIC-11cb25f748d.pdf",
        "key_documentum": "0900f230807c760b"
      }
    ]
  },
  {
    "url_pagina": "https://www1.finanze.gov.it/finanze2/dipartimentopolitichefiscali/fiscalitalocale/nuova_imu/risultato.htm?lista=1&r=1&pagina=molise.htm&cm=&pr=CB&anno=2025&cc=G086",
    "comune": "ORATINO",
    "codice_catastale": "G086",
    "provincia": "CB",
    "delibere": [
      {
        "anno_riferimento": 2025,
        "num_delibera": "25",
        "data_delibera": "10-12-2024",
        "data_pubblicazione": "25-02-2025",
        "codice_tributo": "IMU",
        "note": "",
        "nome_prospetto": "2242_DIMUNIC-11cb25g086d.pdf",
        "link_prospetto": "https://www1.finanze.gov.it/finanze2/dipartimentopolitichefiscali/fiscalitalocale/nuova_imu/download_lib.php?key=0900f2308078e81f&nome=2242_DIMUNIC-11cb25g086d.pdf",
        "key_documentum": "0900f2308078e81f"
      }
    ]
  },
  {
    "url_pagina": "https://www1.finanze.gov.it/finanze2/dipartimentopolitichefiscali/fiscalitalocale/nuova_imu/risultato.htm?lista=1&r=1&pagina=molise.htm&cm=&pr=CB&anno=2025&cc=G257",
    "comune": "PALATA",
    "codice_catastale": "G257",
    "provincia": "CB",
    "delibere": [
      {
        "anno_riferimento": 2025,
        "num_delibera": "38",
        "data_delibera": "27-12-2024",
        "data_pubblicazione": "08-01-2025",
        "codice_tributo": "IMU",
        "note": "",
        "nome_prospetto": "42_DIMUNIC-11cb25g257d.pdf",
        "link_prospetto": "https://www1.finanze.gov.it/finanze2/dipartimentopolitichefiscali/fiscalitalocale/nuova_imu/download_lib.php?key=0900f2308074f674&nome=42_DIMUNIC-11cb25g257d.pdf",
        "key_documentum": "0900f2308074f674"
      }
    ]
  },
  {
    "url_pagina": "https://www1.finanze.gov.it/finanze2/dipartimentopolitichefiscali/fiscalitalocale/nuova_imu/risultato.htm?lista=1&r=1&pagina=molise.htm&cm=&pr=CB&anno=2025&cc=G506",
    "comune": "PETACCIATO",
    "codice_catastale": "G506",
    "provincia": "CB",
    "delibere": [
      {
        "anno_riferimento": 2025,
        "num_delibera": "52",
        "data_delibera": "27-12-2024",
        "data_pubblicazione": "07-02-2025",
        "codice_tributo": "IMU",
        "note": "",
        "nome_prospetto": "3022_DIMUNIC-11cb25g506d.pdf",
        "link_prospetto": "https://www1.finanze.gov.it/finanze2/dipartimentopolitichefiscali/fiscalitalocale/nuova_imu/download_lib.php?key=0900f230807781a8&nome=3022_DIMUNIC-11cb25g506d.pdf",
        "key_documentum": "0900f230807781a8"
      }
    ]
  },
  {
    "url_pagina": "https://www1.finanze.gov.it/finanze2/dipartimentopolitichefiscali/fiscalitalocale/nuova_imu/risultato.htm?lista=1&r=1&pagina=molise.htm&cm=&pr=CB&anno=2025&cc=G512",
    "comune": "PETRELLA TIFERNINA",
    "codice_catastale": "G512",
    "provincia": "CB",
    "delibere": [
      {
        "anno_riferimento": 2025,
        "num_delibera": "39",
        "data_delibera": "23-12-2024",
        "data_pubblicazione": "16-01-2025",
        "codice_tributo": "IMU",
        "note": "",
        "nome_prospetto": "2341_DIMUNIC-11cb25g512d.pdf",
        "link_prospetto": "https://www1.finanze.gov.it/finanze2/dipartimentopolitichefiscali/fiscalitalocale/nuova_imu/download_lib.php?key=0900f23080759947&nome=2341_DIMUNIC-11cb25g512d.pdf",
        "key_documentum": "0900f23080759947"
      }
    ]
  },
  {
    "url_pagina": "https://www1.finanze.gov.it/finanze2/dipartimentopolitichefiscali/fiscalitalocale/nuova_imu/risultato.htm?lista=1&r=1&pagina=molise.htm&cm=&pr=CB&anno=2025&cc=G609",
    "comune": "PIETRACATELLA",
    "codice_catastale": "G609",
    "provincia": "CB",
    "delibere": [
      {
        "anno_riferimento": 2025,
        "num_delibera": "31",
        "data_delibera": "28-12-2024",
        "data_pubblicazione": "03-02-2025",
        "codice_tributo": "IMU",
        "note": "",
        "nome_prospetto": "4245_DIMUNIC-11cb25g609d.pdf",
        "link_prospetto": "https://www1.finanze.gov.it/finanze2/dipartimentopolitichefiscali/fiscalitalocale/nuova_imu/download_lib.php?key=0900f230807696cc&nome=4245_DIMUNIC-11cb25g609d.pdf",
        "key_documentum": "0900f230807696cc"
      }
    ]
  },
  {
    "url_pagina": "https://www1.finanze.gov.it/finanze2/dipartimentopolitichefiscali/fiscalitalocale/nuova_imu/risultato.htm?lista=1&r=1&pagina=molise.htm&cm=&pr=CB&anno=2025&cc=G610",
    "comune": "PIETRACUPA",
    "codice_catastale": "G610",
    "provincia": "CB",
    "delibere": [
      {
        "anno_riferimento": 2025,
        "num_delibera": "2",
        "data_delibera": "28-02-2025",
        "data_pubblicazione": "12-03-2025",
        "codice_tributo": "IMU",
        "note": "",
        "nome_prospetto": "3003_DIMUNIC-11cb25g610d.pdf",
        "link_prospetto": "https://www1.finanze.gov.it/finanze2/dipartimentopolitichefiscali/fiscalitalocale/nuova_imu/download_lib.php?key=0900f230807a674c&nome=3003_DIMUNIC-11cb25g610d.pdf",
        "key_documentum": "0900f230807a674c"
      }
    ]
  },
  {
    "url_pagina": "https://www1.finanze.gov.it/finanze2/dipartimentopolitichefiscali/fiscalitalocale/nuova_imu/risultato.htm?lista=1&r=1&pagina=molise.htm&cm=&pr=CB&anno=2025&cc=G910",
    "comune": "PORTOCANNONE",
    "codice_catastale": "G910",
    "provincia": "CB",
    "delibere": [
      {
        "anno_riferimento": 2025,
        "num_delibera": "31",
        "data_delibera": "23-12-2024",
        "data_pubblicazione": "03-02-2025",
        "codice_tributo": "IMU",
        "note": "",
        "nome_prospetto": "3053_DIMUNIC-11cb25g910d.pdf",
        "link_prospetto": "https://www1.finanze.gov.it/finanze2/dipartimentopolitichefiscali/fiscalitalocale/nuova_imu/download_lib.php?key=0900f23080768c20&nome=3053_DIMUNIC-11cb25g910d.pdf",
        "key_documentum": "0900f23080768c20"
      }
    ]
  },
  {
    "url_pagina": "https://www1.finanze.gov.it/finanze2/dipartimentopolitichefiscali/fiscalitalocale/nuova_imu/risultato.htm?lista=1&r=1&pagina=molise.htm&cm=&pr=CB&anno=2025&cc=H083",
    "comune": "PROVVIDENTI",
    "codice_catastale": "H083",
    "provincia": "CB",
    "delibere": [
      {
        "anno_riferimento": 2025,
        "num_delibera": "5",
        "data_delibera": "26-02-2025",
        "data_pubblicazione": "26-02-2025",
        "codice_tributo": "IMU",
        "note": "",
        "nome_prospetto": "8468_DIMUNIC-11cb25h083d.pdf",
        "link_prospetto": "https://www1.finanze.gov.it/finanze2/dipartimentopolitichefiscali/fiscalitalocale/nuova_imu/download_lib.php?key=0900f2308079473d&nome=8468_DIMUNIC-11cb25h083d.pdf",
        "key_documentum": "0900f2308079473d"
      },
      {
        "anno_riferimento": 2025,
        "num_delibera": "05",
        "data_delibera": "26-02-2025",
        "data_pubblicazione": "28-02-2025",
        "codice_tributo": "IMU",
        "note": "ERRATA CORRIGE PER CORREZIONE DATI PROSPETTO",
        "nome_prospetto": "8586_DIMUNIC-11cb25h083d.pdf",
        "link_prospetto": "https://www1.finanze.gov.it/finanze2/dipartimentopolitichefiscali/fiscalitalocale/nuova_imu/download_lib.php?key=0900f230807947af&nome=8586_DIMUNIC-11cb25h083d.pdf",
        "key_documentum": "0900f230807947af"
      }
    ]
  },
  {
    "url_pagina": "https://www1.finanze.gov.it/finanze2/dipartimentopolitichefiscali/fiscalitalocale/nuova_imu/risultato.htm?lista=1&r=1&pagina=molise.htm&cm=&pr=CB&anno=2025&cc=H273",
    "comune": "RICCIA",
    "codice_catastale": "H273",
    "provincia": "CB",
    "delibere": [
      {
        "anno_riferimento": 2025,
        "num_delibera": "52",
        "data_delibera": "19-12-2024",
        "data_pubblicazione": "03-02-2025",
        "codice_tributo": "IMU",
        "note": "",
        "nome_prospetto": "2952_DIMUNIC-11cb25h273d.pdf",
        "link_prospetto": "https://www1.finanze.gov.it/finanze2/dipartimentopolitichefiscali/fiscalitalocale/nuova_imu/download_lib.php?key=0900f2308076c3fd&nome=2952_DIMUNIC-11cb25h273d.pdf",
        "key_documentum": "0900f2308076c3fd"
      }
    ]
  },
  {
    "url_pagina": "https://www1.finanze.gov.it/finanze2/dipartimentopolitichefiscali/fiscalitalocale/nuova_imu/risultato.htm?lista=1&r=1&pagina=molise.htm&cm=&pr=CB&anno=2025&cc=H311",
    "comune": "RIPABOTTONI",
    "codice_catastale": "H311",
    "provincia": "CB",
    "delibere": [
      {
        "anno_riferimento": 2025,
        "num_delibera": "4",
        "data_delibera": "23-01-2025",
        "data_pubblicazione": "04-02-2025",
        "codice_tributo": "IMU",
        "note": "",
        "nome_prospetto": "6821_DIMUNIC-11cb25h311d.pdf",
        "link_prospetto": "https://www1.finanze.gov.it/finanze2/dipartimentopolitichefiscali/fiscalitalocale/nuova_imu/download_lib.php?key=0900f2308076fbaf&nome=6821_DIMUNIC-11cb25h311d.pdf",
        "key_documentum": "0900f2308076fbaf"
      }
    ]
  },
  {
    "url_pagina": "https://www1.finanze.gov.it/finanze2/dipartimentopolitichefiscali/fiscalitalocale/nuova_imu/risultato.htm?lista=1&r=1&pagina=molise.htm&cm=&pr=CB&anno=2025&cc=H313",
    "comune": "RIPALIMOSANI",
    "codice_catastale": "H313",
    "provincia": "CB",
    "delibere": [
      {
        "anno_riferimento": 2025,
        "num_delibera": "46",
        "data_delibera": "27-12-2024",
        "data_pubblicazione": "01-04-2025",
        "codice_tributo": "IMU",
        "note": "",
        "nome_prospetto": "6302_DIMUNIC-11cb25h313d.pdf",
        "link_prospetto": "https://www1.finanze.gov.it/finanze2/dipartimentopolitichefiscali/fiscalitalocale/nuova_imu/download_lib.php?key=0900f230807c21e7&nome=6302_DIMUNIC-11cb25h313d.pdf",
        "key_documentum": "0900f230807c21e7"
      }
    ]
  },
  {
    "url_pagina": "https://www1.finanze.gov.it/finanze2/dipartimentopolitichefiscali/fiscalitalocale/nuova_imu/risultato.htm?lista=1&r=1&pagina=molise.htm&cm=&pr=CB&anno=2025&cc=H454",
    "comune": "ROCCAVIVARA",
    "codice_catastale": "H454",
    "provincia": "CB",
    "delibere": [
      {
        "anno_riferimento": 2025,
        "num_delibera": "2",
        "data_delibera": "23-02-2025",
        "data_pubblicazione": "17-03-2025",
        "codice_tributo": "IMU",
        "note": "",
        "nome_prospetto": "2325_DIMUNIC-11cb25h454d.pdf",
        "link_prospetto": "https://www1.finanze.gov.it/finanze2/dipartimentopolitichefiscali/fiscalitalocale/nuova_imu/download_lib.php?key=0900f230807aadcd&nome=2325_DIMUNIC-11cb25h454d.pdf",
        "key_documentum": "0900f230807aadcd"
      }
    ]
  },
  {
    "url_pagina": "https://www1.finanze.gov.it/finanze2/dipartimentopolitichefiscali/fiscalitalocale/nuova_imu/risultato.htm?lista=1&r=1&pagina=molise.htm&cm=&pr=CB&anno=2025&cc=H589",
    "comune": "ROTELLO",
    "codice_catastale": "H589",
    "provincia": "CB",
    "delibere": [
      {
        "anno_riferimento": 2025,
        "num_delibera": "29",
        "data_delibera": "23-12-2024",
        "data_pubblicazione": "25-02-2025",
        "codice_tributo": "IMU",
        "note": "",
        "nome_prospetto": "6336_DIMUNIC-11cb25h589d.pdf",
        "link_prospetto": "https://www1.finanze.gov.it/finanze2/dipartimentopolitichefiscali/fiscalitalocale/nuova_imu/download_lib.php?key=0900f23080792728&nome=6336_DIMUNIC-11cb25h589d.pdf",
        "key_documentum": "0900f23080792728"
      }
    ]
  },
  {
    "url_pagina": "https://www1.finanze.gov.it/finanze2/dipartimentopolitichefiscali/fiscalitalocale/nuova_imu/risultato.htm?lista=1&r=1&pagina=molise.htm&cm=&pr=CB&anno=2025&cc=H693",
    "comune": "SALCITO",
    "codice_catastale": "H693",
    "provincia": "CB",
    "delibere": [
      {
        "anno_riferimento": 2025,
        "num_delibera": "8",
        "data_delibera": "03-03-2025",
        "data_pubblicazione": "05-09-2025",
        "codice_tributo": "IMU",
        "note": "",
        "nome_prospetto": "8486_DIMUNIC-11cb25h693d.pdf",
        "link_prospetto": "https://www1.finanze.gov.it/finanze2/dipartimentopolitichefiscali/fiscalitalocale/nuova_imu/download_lib.php?key=0900f230808eacd6&nome=8486_DIMUNIC-11cb25h693d.pdf",
        "key_documentum": "0900f230808eacd6"
      }
    ]
  },
  {
    "url_pagina": "https://www1.finanze.gov.it/finanze2/dipartimentopolitichefiscali/fiscalitalocale/nuova_imu/risultato.htm?lista=1&r=1&pagina=molise.htm&cm=&pr=CB&anno=2025&cc=H782",
    "comune": "SAN BIASE",
    "codice_catastale": "H782",
    "provincia": "CB",
    "delibere": [
      {
        "anno_riferimento": 2025,
        "num_delibera": "5",
        "data_delibera": "22-02-2025",
        "data_pubblicazione": "28-02-2025",
        "codice_tributo": "IMU",
        "note": "",
        "nome_prospetto": "8310_DIMUNIC-11cb25h782d.pdf",
        "link_prospetto": "https://www1.finanze.gov.it/finanze2/dipartimentopolitichefiscali/fiscalitalocale/nuova_imu/download_lib.php?key=0900f23080797813&nome=8310_DIMUNIC-11cb25h782d.pdf",
        "key_documentum": "0900f23080797813"
      }
    ]
  },
  {
    "url_pagina": "https://www1.finanze.gov.it/finanze2/dipartimentopolitichefiscali/fiscalitalocale/nuova_imu/risultato.htm?lista=1&r=1&pagina=molise.htm&cm=&pr=CB&anno=2025&cc=H833",
    "comune": "SAN FELICE DEL MOLISE",
    "codice_catastale": "H833",
    "provincia": "CB",
    "delibere": [
      {
        "anno_riferimento": 2025,
        "num_delibera": "45",
        "data_delibera": "12-12-2024",
        "data_pubblicazione": "12-03-2025",
        "codice_tributo": "IMU",
        "note": "",
        "nome_prospetto": "2067_DIMUNIC-11cb25h833d.pdf",
        "link_prospetto": "https://www1.finanze.gov.it/finanze2/dipartimentopolitichefiscali/fiscalitalocale/nuova_imu/download_lib.php?key=0900f230807a705c&nome=2067_DIMUNIC-11cb25h833d.pdf",
        "key_documentum": "0900f230807a705c"
      }
    ]
  },
  {
    "url_pagina": "https://www1.finanze.gov.it/finanze2/dipartimentopolitichefiscali/fiscalitalocale/nuova_imu/risultato.htm?lista=1&r=1&pagina=molise.htm&cm=&pr=CB&anno=2025&cc=H867",
    "comune": "SAN GIACOMO DEGLI SCHIAVONI",
    "codice_catastale": "H867",
    "provincia": "CB",
    "delibere": [
      {
        "anno_riferimento": 2025,
        "num_delibera": "5",
        "data_delibera": "28-03-2025",
        "data_pubblicazione": "03-04-2025",
        "codice_tributo": "IMU",
        "note": "",
        "nome_prospetto": "8801_DIMUNIC-11cb25h867d.pdf",
        "link_prospetto": "https://www1.finanze.gov.it/finanze2/dipartimentopolitichefiscali/fiscalitalocale/nuova_imu/download_lib.php?key=0900f230807c3ef1&nome=8801_DIMUNIC-11cb25h867d.pdf",
        "key_documentum": "0900f230807c3ef1"
      }
    ]
  },
  {
    "url_pagina": "https://www1.finanze.gov.it/finanze2/dipartimentopolitichefiscali/fiscalitalocale/nuova_imu/risultato.htm?lista=1&r=1&pagina=molise.htm&cm=&pr=CB&anno=2025&cc=H920",
    "comune": "SAN GIOVANNI IN GALDO",
    "codice_catastale": "H920",
    "provincia": "CB",
    "delibere": [
      {
        "anno_riferimento": 2025,
        "num_delibera": "24",
        "data_delibera": "16-12-2024",
        "data_pubblicazione": "04-03-2025",
        "codice_tributo": "IMU",
        "note": "",
        "nome_prospetto": "6772_DIMUNIC-11cb25h920d.pdf",
        "link_prospetto": "https://www1.finanze.gov.it/finanze2/dipartimentopolitichefiscali/fiscalitalocale/nuova_imu/download_lib.php?key=0900f2308079b70e&nome=6772_DIMUNIC-11cb25h920d.pdf",
        "key_documentum": "0900f2308079b70e"
      }
    ]
  },
  {
    "url_pagina": "https://www1.finanze.gov.it/finanze2/dipartimentopolitichefiscali/fiscalitalocale/nuova_imu/risultato.htm?lista=1&r=1&pagina=molise.htm&cm=&pr=CB&anno=2025&cc=H928",
    "comune": "SAN GIULIANO DEL SANNIO",
    "codice_catastale": "H928",
    "provincia": "CB",
    "delibere": [
      {
        "anno_riferimento": 2025,
        "num_delibera": "25",
        "data_delibera": "19-12-2024",
        "data_pubblicazione": "14-01-2025",
        "codice_tributo": "IMU",
        "note": "",
        "nome_prospetto": "4498_DIMUNIC-11cb25h928d.pdf",
        "link_prospetto": "https://www1.finanze.gov.it/finanze2/dipartimentopolitichefiscali/fiscalitalocale/nuova_imu/download_lib.php?key=0900f230807542c3&nome=4498_DIMUNIC-11cb25h928d.pdf",
        "key_documentum": "0900f230807542c3"
      }
    ]
  },
  {
    "url_pagina": "https://www1.finanze.gov.it/finanze2/dipartimentopolitichefiscali/fiscalitalocale/nuova_imu/risultato.htm?lista=1&r=1&pagina=molise.htm&cm=&pr=CB&anno=2025&cc=H929",
    "comune": "SAN GIULIANO DI PUGLIA",
    "codice_catastale": "H929",
    "provincia": "CB",
    "delibere": [
      {
        "anno_riferimento": 2025,
        "num_delibera": "37",
        "data_delibera": "27-12-2024",
        "data_pubblicazione": "09-01-2025",
        "codice_tributo": "IMU",
        "note": "",
        "nome_prospetto": "6396_DIMUNIC-11cb25h929d.pdf",
        "link_prospetto": "https://www1.finanze.gov.it/finanze2/dipartimentopolitichefiscali/fiscalitalocale/nuova_imu/download_lib.php?key=0900f23080751732&nome=6396_DIMUNIC-11cb25h929d.pdf",
        "key_documentum": "0900f23080751732"
      }
    ]
  },
  {
    "url_pagina": "https://www1.finanze.gov.it/finanze2/dipartimentopolitichefiscali/fiscalitalocale/nuova_imu/risultato.htm?lista=1&r=1&pagina=molise.htm&cm=&pr=CB&anno=2025&cc=H990",
    "comune": "SAN MARTINO IN PENSILIS",
    "codice_catastale": "H990",
    "provincia": "CB",
    "delibere": [
      {
        "anno_riferimento": 2025,
        "num_delibera": "2",
        "data_delibera": "31-01-2025",
        "data_pubblicazione": "13-02-2025",
        "codice_tributo": "IMU",
        "note": "",
        "nome_prospetto": "6848_DIMUNIC-11cb25h990d.pdf",
        "link_prospetto": "https://www1.finanze.gov.it/finanze2/dipartimentopolitichefiscali/fiscalitalocale/nuova_imu/download_lib.php?key=0900f2308077d4ff&nome=6848_DIMUNIC-11cb25h990d.pdf",
        "key_documentum": "0900f2308077d4ff"
      },
      {
        "anno_riferimento": 2025,
        "num_delibera": "26",
        "data_delibera": "24-10-2025",
        "data_pubblicazione": "10-11-2025",
        "codice_tributo": "IMU",
        "note": "AUTOTUTELA EX ART. 21-NONIES, L. 241/1990",
        "nome_prospetto": "12243_DIMUNIC-11cb25h990d.pdf",
        "link_prospetto": "https://www1.finanze.gov.it/finanze2/dipartimentopolitichefiscali/fiscalitalocale/nuova_imu/download_lib.php?key=0900f23080a913e2&nome=12243_DIMUNIC-11cb25h990d.pdf",
        "key_documentum": "0900f23080a913e2"
      }
    ]
  },
  {
    "url_pagina": "https://www1.finanze.gov.it/finanze2/dipartimentopolitichefiscali/fiscalitalocale/nuova_imu/risultato.htm?lista=1&r=1&pagina=molise.htm&cm=&pr=CB&anno=2025&cc=I023",
    "comune": "SAN MASSIMO",
    "codice_catastale": "I023",
    "provincia": "CB",
    "delibere": [
      {
        "anno_riferimento": 2025,
        "num_delibera": "3",
        "data_delibera": "14-03-2025",
        "data_pubblicazione": "26-03-2025",
        "codice_tributo": "IMU",
        "note": "",
        "nome_prospetto": "6535_DIMUNIC-11cb25i023d.pdf",
        "link_prospetto": "https://www1.finanze.gov.it/finanze2/dipartimentopolitichefiscali/fiscalitalocale/nuova_imu/download_lib.php?key=0900f230807ba05c&nome=6535_DIMUNIC-11cb25i023d.pdf",
        "key_documentum": "0900f230807ba05c"
      }
    ]
  },
  {
    "url_pagina": "https://www1.finanze.gov.it/finanze2/dipartimentopolitichefiscali/fiscalitalocale/nuova_imu/risultato.htm?lista=1&r=1&pagina=molise.htm&cm=&pr=CB&anno=2025&cc=I122",
    "comune": "SAN POLO MATESE",
    "codice_catastale": "I122",
    "provincia": "CB",
    "delibere": [
      {
        "anno_riferimento": 2025,
        "num_delibera": "34",
        "data_delibera": "20-12-2024",
        "data_pubblicazione": "19-08-2025",
        "codice_tributo": "IMU",
        "note": "",
        "nome_prospetto": "6048_DIMUNIC-11cb25i122d.pdf",
        "link_prospetto": "https://www1.finanze.gov.it/finanze2/dipartimentopolitichefiscali/fiscalitalocale/nuova_imu/download_lib.php?key=0900f230808e2679&nome=6048_DIMUNIC-11cb25i122d.pdf",
        "key_documentum": "0900f230808e2679"
      }
    ]
  },
  {
    "url_pagina": "https://www1.finanze.gov.it/finanze2/dipartimentopolitichefiscali/fiscalitalocale/nuova_imu/risultato.htm?lista=1&r=1&pagina=molise.htm&cm=&pr=CB&anno=2025&cc=I181",
    "comune": "SANTA CROCE DI MAGLIANO",
    "codice_catastale": "I181",
    "provincia": "CB",
    "delibere": [
      {
        "anno_riferimento": 2025,
        "num_delibera": "7",
        "data_delibera": "27-02-2025",
        "data_pubblicazione": "17-03-2025",
        "codice_tributo": "IMU",
        "note": "",
        "nome_prospetto": "7990_DIMUNIC-11cb25i181d.pdf",
        "link_prospetto": "https://www1.finanze.gov.it/finanze2/dipartimentopolitichefiscali/fiscalitalocale/nuova_imu/download_lib.php?key=0900f230807aa653&nome=7990_DIMUNIC-11cb25i181d.pdf",
        "key_documentum": "0900f230807aa653"
      }
    ]
  },
  {
    "url_pagina": "https://www1.finanze.gov.it/finanze2/dipartimentopolitichefiscali/fiscalitalocale/nuova_imu/risultato.htm?lista=1&r=1&pagina=molise.htm&cm=&pr=CB&anno=2025&cc=I289",
    "comune": "SANT'ANGELO LIMOSANO",
    "codice_catastale": "I289",
    "provincia": "CB",
    "delibere": [
      {
        "anno_riferimento": 2025,
        "num_delibera": "7",
        "data_delibera": "05-04-2025",
        "data_pubblicazione": "19-05-2025",
        "codice_tributo": "IMU",
        "note": "",
        "nome_prospetto": "8887_DIMUNIC-11cb25i289d.pdf",
        "link_prospetto": "https://www1.finanze.gov.it/finanze2/dipartimentopolitichefiscali/fiscalitalocale/nuova_imu/download_lib.php?key=0900f230807fdbb5&nome=8887_DIMUNIC-11cb25i289d.pdf",
        "key_documentum": "0900f230807fdbb5"
      },
      {
        "anno_riferimento": 2025,
        "num_delibera": "20",
        "data_delibera": "09-09-2025",
        "data_pubblicazione": "01-10-2025",
        "codice_tributo": "IMU",
        "note": "",
        "nome_prospetto": "11562_DIMUNIC-11cb25i289d.pdf",
        "link_prospetto": "https://www1.finanze.gov.it/finanze2/dipartimentopolitichefiscali/fiscalitalocale/nuova_imu/download_lib.php?key=0900f2308090b554&nome=11562_DIMUNIC-11cb25i289d.pdf",
        "key_documentum": "0900f2308090b554"
      }
    ]
  },
  {
    "url_pagina": "https://www1.finanze.gov.it/finanze2/dipartimentopolitichefiscali/fiscalitalocale/nuova_imu/risultato.htm?lista=1&r=1&pagina=molise.htm&cm=&pr=CB&anno=2025&cc=I320",
    "comune": "SANT'ELIA A PIANISI",
    "codice_catastale": "I320",
    "provincia": "CB",
    "delibere": [
      {
        "anno_riferimento": 2025,
        "num_delibera": "36",
        "data_delibera": "04-12-2024",
        "data_pubblicazione": "27-02-2025",
        "codice_tributo": "IMU",
        "note": "",
        "nome_prospetto": "2853_DIMUNIC-11cb25i320d.pdf",
        "link_prospetto": "https://www1.finanze.gov.it/finanze2/dipartimentopolitichefiscali/fiscalitalocale/nuova_imu/download_lib.php?key=0900f23080795996&nome=2853_DIMUNIC-11cb25i320d.pdf",
        "key_documentum": "0900f23080795996"
      }
    ]
  },
  {
    "url_pagina": "https://www1.finanze.gov.it/finanze2/dipartimentopolitichefiscali/fiscalitalocale/nuova_imu/risultato.htm?lista=1&r=1&pagina=molise.htm&cm=&pr=CB&anno=2025&cc=I618",
    "comune": "SEPINO",
    "codice_catastale": "I618",
    "provincia": "CB",
    "delibere": [
      {
        "anno_riferimento": 2025,
        "num_delibera": "23",
        "data_delibera": "29-11-2024",
        "data_pubblicazione": "09-01-2025",
        "codice_tributo": "IMU",
        "note": "",
        "nome_prospetto": "2064_DIMUNIC-11cb25i618d.pdf",
        "link_prospetto": "https://www1.finanze.gov.it/finanze2/dipartimentopolitichefiscali/fiscalitalocale/nuova_imu/download_lib.php?key=0900f2308074f2f1&nome=2064_DIMUNIC-11cb25i618d.pdf",
        "key_documentum": "0900f2308074f2f1"
      }
    ]
  },
  {
    "url_pagina": "https://www1.finanze.gov.it/finanze2/dipartimentopolitichefiscali/fiscalitalocale/nuova_imu/risultato.htm?lista=1&r=1&pagina=molise.htm&cm=&pr=CB&anno=2025&cc=I910",
    "comune": "SPINETE",
    "codice_catastale": "I910",
    "provincia": "CB",
    "delibere": [
      {
        "anno_riferimento": 2025,
        "num_delibera": "29",
        "data_delibera": "23-12-2024",
        "data_pubblicazione": "03-01-2025",
        "codice_tributo": "IMU",
        "note": "",
        "nome_prospetto": "3301_DIMUNIC-11cb25i910d.pdf",
        "link_prospetto": "https://www1.finanze.gov.it/finanze2/dipartimentopolitichefiscali/fiscalitalocale/nuova_imu/download_lib.php?key=0900f2308074d5e8&nome=3301_DIMUNIC-11cb25i910d.pdf",
        "key_documentum": "0900f2308074d5e8"
      }
    ]
  },
  {
    "url_pagina": "https://www1.finanze.gov.it/finanze2/dipartimentopolitichefiscali/fiscalitalocale/nuova_imu/risultato.htm?lista=1&r=1&pagina=molise.htm&cm=&pr=CB&anno=2025&cc=L069",
    "comune": "TAVENNA",
    "codice_catastale": "L069",
    "provincia": "CB",
    "delibere": [
      {
        "anno_riferimento": 2025,
        "num_delibera": "33",
        "data_delibera": "28-12-2024",
        "data_pubblicazione": "26-02-2025",
        "codice_tributo": "IMU",
        "note": "",
        "nome_prospetto": "5906_DIMUNIC-11cb25l069d.pdf",
        "link_prospetto": "https://www1.finanze.gov.it/finanze2/dipartimentopolitichefiscali/fiscalitalocale/nuova_imu/download_lib.php?key=0900f23080793c69&nome=5906_DIMUNIC-11cb25l069d.pdf",
        "key_documentum": "0900f23080793c69"
      }
    ]
  },
  {
    "url_pagina": "https://www1.finanze.gov.it/finanze2/dipartimentopolitichefiscali/fiscalitalocale/nuova_imu/risultato.htm?lista=1&r=1&pagina=molise.htm&cm=&pr=CB&anno=2025&cc=L113",
    "comune": "TERMOLI",
    "codice_catastale": "L113",
    "provincia": "CB",
    "delibere": [
      {
        "anno_riferimento": 2025,
        "num_delibera": "81",
        "data_delibera": "27-11-2024",
        "data_pubblicazione": "28-02-2025",
        "codice_tributo": "IMU",
        "note": "",
        "nome_prospetto": "669_DIMUNIC-11cb25l113d.pdf",
        "link_prospetto": "https://www1.finanze.gov.it/finanze2/dipartimentopolitichefiscali/fiscalitalocale/nuova_imu/download_lib.php?key=0900f23080797d5b&nome=669_DIMUNIC-11cb25l113d.pdf",
        "key_documentum": "0900f23080797d5b"
      }
    ]
  },
  {
    "url_pagina": "https://www1.finanze.gov.it/finanze2/dipartimentopolitichefiscali/fiscalitalocale/nuova_imu/risultato.htm?lista=1&r=1&pagina=molise.htm&cm=&pr=CB&anno=2025&cc=L215",
    "comune": "TORELLA DEL SANNIO",
    "codice_catastale": "L215",
    "provincia": "CB",
    "delibere": [
      {
        "anno_riferimento": 2025,
        "num_delibera": "26",
        "data_delibera": "27-12-2024",
        "data_pubblicazione": "01-04-2025",
        "codice_tributo": "IMU",
        "note": "",
        "nome_prospetto": "6147_DIMUNIC-11cb25l215d.pdf",
        "link_prospetto": "https://www1.finanze.gov.it/finanze2/dipartimentopolitichefiscali/fiscalitalocale/nuova_imu/download_lib.php?key=0900f230807c0fc7&nome=6147_DIMUNIC-11cb25l215d.pdf",
        "key_documentum": "0900f230807c0fc7"
      }
    ]
  },
  {
    "url_pagina": "https://www1.finanze.gov.it/finanze2/dipartimentopolitichefiscali/fiscalitalocale/nuova_imu/risultato.htm?lista=1&r=1&pagina=molise.htm&cm=&pr=CB&anno=2025&cc=L230",
    "comune": "TORO",
    "codice_catastale": "L230",
    "provincia": "CB",
    "delibere": [
      {
        "anno_riferimento": 2025,
        "num_delibera": "28",
        "data_delibera": "30-12-2024",
        "data_pubblicazione": "24-03-2025",
        "codice_tributo": "IMU",
        "note": "",
        "nome_prospetto": "3999_DIMUNIC-11cb25l230d.pdf",
        "link_prospetto": "https://www1.finanze.gov.it/finanze2/dipartimentopolitichefiscali/fiscalitalocale/nuova_imu/download_lib.php?key=0900f230807b6cc3&nome=3999_DIMUNIC-11cb25l230d.pdf",
        "key_documentum": "0900f230807b6cc3"
      }
    ]
  },
  {
    "url_pagina": "https://www1.finanze.gov.it/finanze2/dipartimentopolitichefiscali/fiscalitalocale/nuova_imu/risultato.htm?lista=1&r=1&pagina=molise.htm&cm=&pr=CB&anno=2025&cc=L435",
    "comune": "TRIVENTO",
    "codice_catastale": "L435",
    "provincia": "CB",
    "delibere": [
      {
        "anno_riferimento": 2025,
        "num_delibera": "54",
        "data_delibera": "28-12-2024",
        "data_pubblicazione": "09-01-2025",
        "codice_tributo": "IMU",
        "note": "",
        "nome_prospetto": "1791_DIMUNIC-11cb25l435d.pdf",
        "link_prospetto": "https://www1.finanze.gov.it/finanze2/dipartimentopolitichefiscali/fiscalitalocale/nuova_imu/download_lib.php?key=0900f2308075142c&nome=1791_DIMUNIC-11cb25l435d.pdf",
        "key_documentum": "0900f2308075142c"
      }
    ]
  },
  {
    "url_pagina": "https://www1.finanze.gov.it/finanze2/dipartimentopolitichefiscali/fiscalitalocale/nuova_imu/risultato.htm?lista=1&r=1&pagina=molise.htm&cm=&pr=CB&anno=2025&cc=L458",
    "comune": "TUFARA",
    "codice_catastale": "L458",
    "provincia": "CB",
    "delibere": [
      {
        "anno_riferimento": 2025,
        "num_delibera": "39",
        "data_delibera": "23-12-2024",
        "data_pubblicazione": "14-01-2025",
        "codice_tributo": "IMU",
        "note": "",
        "nome_prospetto": "1517_DIMUNIC-11cb25l458d.pdf",
        "link_prospetto": "https://www1.finanze.gov.it/finanze2/dipartimentopolitichefiscali/fiscalitalocale/nuova_imu/download_lib.php?key=0900f230807540f4&nome=1517_DIMUNIC-11cb25l458d.pdf",
        "key_documentum": "0900f230807540f4"
      }
    ]
  },
  {
    "url_pagina": "https://www1.finanze.gov.it/finanze2/dipartimentopolitichefiscali/fiscalitalocale/nuova_imu/risultato.htm?lista=1&r=1&pagina=molise.htm&cm=&pr=CB&anno=2025&cc=L505",
    "comune": "URURI",
    "codice_catastale": "L505",
    "provincia": "CB",
    "delibere": [
      {
        "anno_riferimento": 2025,
        "num_delibera": "6",
        "data_delibera": "25-02-2025",
        "data_pubblicazione": "28-02-2025",
        "codice_tributo": "IMU",
        "note": "",
        "nome_prospetto": "2304_DIMUNIC-11cb25l505d.pdf",
        "link_prospetto": "https://www1.finanze.gov.it/finanze2/dipartimentopolitichefiscali/fiscalitalocale/nuova_imu/download_lib.php?key=0900f23080797b75&nome=2304_DIMUNIC-11cb25l505d.pdf",
        "key_documentum": "0900f23080797b75"
      }
    ]
  },
  {
    "url_pagina": "https://www1.finanze.gov.it/finanze2/dipartimentopolitichefiscali/fiscalitalocale/nuova_imu/risultato.htm?lista=1&r=1&pagina=molise.htm&cm=&pr=CB&anno=2025&cc=M057",
    "comune": "VINCHIATURO",
    "codice_catastale": "M057",
    "provincia": "CB",
    "delibere": [
      {
        "anno_riferimento": 2025,
        "num_delibera": "25",
        "data_delibera": "17-12-2024",
        "data_pubblicazione": "03-02-2025",
        "codice_tributo": "IMU",
        "note": "",
        "nome_prospetto": "2533_DIMUNIC-11cb25m057d.pdf",
        "link_prospetto": "https://www1.finanze.gov.it/finanze2/dipartimentopolitichefiscali/fiscalitalocale/nuova_imu/download_lib.php?key=0900f23080764ad4&nome=2533_DIMUNIC-11cb25m057d.pdf",
        "key_documentum": "0900f23080764ad4"
      }
    ]
  }
]